Workbook

Sheet stocks-list
A1: Symbol | B1: Company Name | C1: Industry | D1: Market Cap | F1: {=_xlfn._xlws.SORT(_xlfn.UNIQUE(C2:C5544))} -> Advertising Agencies | G1: =COUNTA(F1:F152) -> 152
A2: A | B2: Agilent Technologies, Inc. | C2: Diagnostics & Research | D2: 32182751860 | F2: Aerospace & Defense
A3: AA | B3: Alcoa Corporation | C3: Aluminum | D3: 19196003568 | F3: Agricultural Inputs
A4: AACB | B4: Artius II Acquisition Inc. | C4: Shell Companies | D4: 286159500 | F4: Airlines
A5: AACG | B5: ATA Creativity Global | C5: Education & Training Services | D5: 42179728 | F5: Airports & Air Services
A6: AACI | B6: Armada Acquisition Corp. III | C6: Shell Companies | D6: 71742845 | F6: Aluminum
A7: AACO | B7: Abony Acquisition Corp. I | C7: Shell Companies | D7: 312048587 | F7: Apparel Manufacturing
A8: AACP | B8: Apogee Acquisition Corp | C8: Shell Companies | D8: 205518800 | F8: Apparel Retail
A9: AAL | B9: American Airlines Group Inc. | C9: Airlines | D9: 7055354363 | F9: Asset Management
A10: AAME | B10: Atlantic American Corporation | C10: Insurance - Life | D10: 48545403 | F10: Asset Management - Income
A11: AAMI | B11: Acadian Asset Management Inc. | C11: Asset Management | D11: 2016896189 | F11: Auto & Truck Dealerships
A12: AAOI | B12: Applied Optoelectronics, Inc. | C12: Communication Equipment | D12: 8933416011 | F12: Auto Manufacturers
A13: AAON | B13: AAON, Inc. | C13: Building Products & Equipment | D13: 6563998161 | F13: Auto Parts
... A152: AGMB | B152: AgomAb Therapeutics NV | C152: Biotechnology | D152: 511248812 | F152: Waste Management
A153: AGMH | B153: AGM Group Holdings Inc. | C153: Computer Hardware | D153: 2012024
A154: AGNC | B154: AGNC Investment Corp. | C154: REIT - Mortgage | D154: 11361565712
A155: AGNCM | B155: AGNC Investment Corp. | C155: REIT - Mortgage | D155: 8435896208
A156: AGO | B156: Assured Guaranty Ltd. | C156: Insurance - Specialty | D156: 3670572112
A157: AGPU | B157: Axe Compute Inc. | C157: Software - Infrastructure | D157: 29413508
A158: AGRO | B158: Adecoagro S.A. | C158: Farm Products | D158: 2118691040
A159: AGRZ | B159: Agroz Inc. | C159: Farm Products | D159: 9633864
A160: AGX | B160: Argan, Inc. | C160: Engineering & Construction | D160: 7935810216
A161: AGYS | B161: Agilysys, Inc. | C161: Software - Application | D161: 1939247672
A162: AHCO | B162: AdaptHealth Corp. | C162: Medical Devices | D162: 1628259496
A163: AHG | B163: Akso Health Group | C163: Medical Distribution | D163: 1906166792
A164: AHMA | B164: Ambitions Enterprise Management Co. L.L.C | C164: Travel Services | D164: 29427750
... A1264: CRNC | B1264: Cerence Inc. | C1264: Software - Application | D1264: 342587604
A1265: CRNG | B1265: CorEnergy Infrastructure Trust, Inc. | C1265: Specialty Business Services
A1266: CRNT | B1266: Ceragon Networks Ltd. | C1266: Communication Equipment | D1266: 202252430
A1267: CRNX | B1267: Crinetics Pharmaceuticals, Inc. | C1267: Biotechnology | D1267: 3965190847
A1268: CRON | B1268: Cronos Group Inc. | C1268: Drug Manufacturers - Specialty & Generic | D1268: 973085797
A1269: CROX | B1269: Crocs, Inc. | C1269: Footwear & Accessories | D1269: 4573266580
A1270: CRS | B1270: Carpenter Technology Corporation | C1270: Metal Fabrication | D1270: 19581195947
A1271: CRSP | B1271: CRISPR Therapeutics AG | C1271: Biotechnology | D1271: 4758951769
A1272: CRSR | B1272: Corsair Gaming, Inc. | C1272: Computer Hardware | D1272: 597842399
A1273: CRT | B1273: Cross Timbers Royalty Trust | C1273: Oil & Gas Exploration & Production | D1273: 64260000
A1274: CRTO | B1274: Criteo S.A. | C1274: Advertising Agencies | D1274: 920897318
A1275: CRUS | B1275: Cirrus Logic, Inc. | C1275: Semiconductors | D1275: 7491455222
A1276: CRVL | B1276: CorVel Corporation | C1276: Insurance Brokers | D1276: 2859932753
A1277: CRVO | B1277: CervoMed Inc. | C1277: Biotechnology | D1277: 36294178
... A2242: H | B2242: Hyatt Hotels Corporation | C2242: Lodging | D2242: 13541009435
A2243: HACQ | B2243: HCM IV Acquisition Corp. | C2243: Shell Companies
A2244: HAE | B2244: Haemonetics Corporation | C2244: Medical Devices | D2244: 2773410168
A2245: HAFC | B2245: Hanmi Financial Corporation | C2245: Banks - Regional | D2245: 799418281
A2246: HAFN | B2246: Hafnia Limited | C2246: Marine Shipping | D2246: 4048228571
A2247: HAIN | B2247: The Hain Celestial Group, Inc. | C2247: Packaged Foods | D2247: 70119005
A2248: HAL | B2248: Halliburton Company | C2248: Oil & Gas Equipment & Services | D2248: 31923893794
A2249: HALO | B2249: Halozyme Therapeutics, Inc. | C2249: Biotechnology | D2249: 7546812910
A2250: HAO | B2250: Haoxi Health Technology Limited | C2250: Advertising Agencies | D2250: 60044211
A2251: HAS | B2251: Hasbro, Inc. | C2251: Leisure | D2251: 12600519915
A2252: HASI | B2252: HA Sustainable Infrastructure Capital, Inc. | C2252: Asset Management | D2252: 4554673811
A2253: HAVA | B2253: Harvard Ave Acquisition Corporation | C2253: Shell Companies | D2253: 158757159
A2254: HAYW | B2254: Hayward Holdings, Inc. | C2254: Electrical Equipment & Parts | D2254: 2936647550
A2255: HBAN | B2255: Huntington Bancshares Incorporated | C2255: Banks - Regional | D2255: 32217047423
... A3355: MZTI | B3355: The Marzetti Company | C3355: Packaged Foods | D3355: 3978940185
A3356: MZYX | B3356: MOZAYYX Acquisition Corp. | C3356: Shell Companies
A3357: NA | B3357: Nano Labs Ltd | C3357: Semiconductors | D3357: 68426885
A3358: NAAS | B3358: NaaS Technology Inc. | C3358: Specialty Retail | D3358: 29173548
A3359: NABL | B3359: N-able, Inc. | C3359: Information Technology Services | D3359: 902322554
A3360: NAGE | B3360: Niagen Bioscience, Inc. | C3360: Biotechnology | D3360: 359107509
A3361: NAII | B3361: Natural Alternatives International, Inc. | C3361: Packaged Foods | D3361: 15847374
A3362: NAK | B3362: Northern Dynasty Minerals Ltd. | C3362: Other Industrial Metals & Mining | D3362: 842613821
A3363: NAKA | B3363: Nakamoto Inc. | C3363: Capital Markets | D3363: 147870912
A3364: NAMI | B3364: Jinxin Technology Holding Company | C3364: Internet Content & Information | D3364: 35195428
A3365: NAMM | B3365: Namib Minerals | C3365: Gold | D3365: 119589432
A3366: NAMS | B3366: NewAmsterdam Pharma Company N.V. | C3366: Biotechnology | D3366: 3875821476
A3367: NAT | B3367: Nordic American Tankers Limited | C3367: Oil & Gas Midstream | D3367: 1283209018
A3368: NATH | B3368: Nathan's Famous, Inc. | C3368: Restaurants | D3368: 412552248
... A3637: OFS | B3637: OFS Capital Corporation | C3637: Asset Management | D3637: 47697158
A3638: OGC | B3638: OceanaGold Corporation | C3638: Other Precious Metals & Mining
A3639: OGE | B3639: OGE Energy Corp. | C3639: Utilities - Regulated Electric | D3639: 10153571723
A3640: OGEN | B3640: Oragenics, Inc. | C3640: Biotechnology | D3640: 2469369
A3641: OGI | B3641: Organigram Global Inc. | C3641: Drug Manufacturers - Specialty & Generic | D3641: 186100005
A3642: OGN | B3642: Organon & Co. | C3642: Drug Manufacturers - General | D3642: 1584020730
A3643: OGS | B3643: ONE Gas, Inc. | C3643: Utilities - Regulated Gas | D3643: 5630378123
A3644: OHI | B3644: Omega Healthcare Investors, Inc. | C3644: REIT - Healthcare Facilities | D3644: 13983867350
A3645: OI | B3645: O-I Glass, Inc. | C3645: Packaging & Containers | D3645: 1566277341
A3646: OII | B3646: Oceaneering International, Inc. | C3646: Oil & Gas Equipment & Services | D3646: 3706392676
A3647: OIM | B3647: Oneim Acquisition Corp. | C3647: Shell Companies | D3647: 292684500
A3648: OIO | B3648: OIO Group | C3648: Asset Management | D3648: 132260669
A3649: OIS | B3649: Oil States International, Inc. | C3649: Oil & Gas Equipment & Services | D3649: 676645831
A3650: OKE | B3650: ONEOK, Inc. | C3650: Oil & Gas Midstream | D3650: 56847663204
... A5544: ZYME | B5544: Zymeworks Inc. | C5544: Biotechnology | D5544: 1886514947

Sheet string-format
A1: {='stocks-list'!A1:C1} -> Symbol | B1: Company Name | C1: Industry
A2: {=CHAR(34)&'stocks-list'!A2:C5544&CHAR(34)} -> "A" | B2: "Agilent Technologies, Inc." | C2: "Diagnostics & Research"
A3: "AA" | B3: "Alcoa Corporation" | C3: "Aluminum"
A4: "AACB" | B4: "Artius II Acquisition Inc." | C4: "Shell Companies"
A5: "AACG" | B5: "ATA Creativity Global" | C5: "Education & Training Services"
A6: "AACI" | B6: "Armada Acquisition Corp. III" | C6: "Shell Companies"
A7: "AACO" | B7: "Abony Acquisition Corp. I" | C7: "Shell Companies"
A8: "AACP" | B8: "Apogee Acquisition Corp" | C8: "Shell Companies"
A9: "AAL" | B9: "American Airlines Group Inc." | C9: "Airlines"
A10: "AAME" | B10: "Atlantic American Corporation" | C10: "Insurance - Life"
A11: "AAMI" | B11: "Acadian Asset Management Inc." | C11: "Asset Management"
A12: "AAOI" | B12: "Applied Optoelectronics, Inc." | C12: "Communication Equipment"
A13: "AAON" | B13: "AAON, Inc." | C13: "Building Products & Equipment"
A14: "AAP" | B14: "Advance Auto Parts, Inc." | C14: "Auto Parts"
... A5544: "ZYME" | B5544: "Zymeworks Inc." | C5544: "Biotechnology"

Sheet sort-ticker-by-industry
A1: Industry | B1: Symbol Starts Here | C1: =COUNTA(A2:A200) & " Unique Industries" -> 152 Unique Industries
A2: {=_xlfn._xlws.SORT(_xlfn.UNIQUE('stocks-list'!C2:C5544))} -> Advertising Agencies | B2: {=TRANSPOSE(_xlfn._xlws.FILTER('stocks-list'!A2:A5544, 'stocks-list'!C2:C5544=A2, ""))} -> ACCS | C2: ADV | D2: APP | E2: BAOS | F2: CCO | G2: CDLX | H2: CHR | I2: CNET | J2: CRTO | K2: DLPN | L2: DRCT | M2: DV | N2: EDHL | O2: EEX | P2: EVC | Q2: FLNT | R2: HAO | S2: KRKR | T2: MCHX | U2: MGNI | V2: NCMI | W2: NEXN | X2: OMC | Y2: QMMM | Z2: QNST | AA2: SDM | AB2: SOPA | AC2: STFS | AD2: STGW | AE2: SWAG | AF2: TC | AG2: TDIC | AH2: TJGC | AI2: TSQ | AJ2: TTD | AK2: TULP | AL2: VSME | AM2: WIMI | AN2: WPP | AO2: YDKG | AP2: ZD
A3: Aerospace & Defense | B3: {=TRANSPOSE(_xlfn._xlws.FILTER('stocks-list'!A3:A5545, 'stocks-list'!C3:C5545=A3, ""))} -> ACHR | C3: AIR | D3: AIRI | E3: AIRO | F3: ATRO | G3: AVAV | H3: AXON | I3: BA | J3: BETA | K3: BWXT | L3: BYRN | M3: CAE | N3: CDRE | O3: CODA | P3: CVU | Q3: CW | R3: DCO | S3: DFNS | T3: DFSC | U3: DRS | V3: EH | W3: EMBJ | X3: ESLT | Y3: EVEX | Z3: EVTL | AA3: FJET | AB3: FLY | AC3: GD | AD3: GE | AE3: GPUS | AF3: HEI | AG3: HEI.A | AH3: HII | AI3: HOVR | AJ3: HWM | AK3: HXL | AL3: ISSC | AM3: KITT | AN3: KRMN | AO3: KTOS | AP3: LHX | AQ3: LMT | AR3: LOAR | AS3: LUNR | AT3: MDA | AU3: MNTS | AV3: MOB | AW3: MOG.A | AX3: MOG.B | AY3: MRCY | AZ3: MRLN | BA3: NOC | BB3: NPK | BC3: OPXS | BD3: PEW | BE3: PKE | BF3: PL | BG3: POWW | BH3: PRZO | BI3: RCAT | BJ3: RDW | BK3: RGR | BL3: RKLB | BM3: RTX | BN3: SARO | BO3: SATL | BP3: SDEV | BQ3: SIDU | BR3: SIF | BS3: SPAI | BT3: SPCE | BU3: SWBI | BV3: SWMR | BW3: TATT | BX3: TDG | BY3: TXT | BZ3: VOYG | CA3: VSEC | CB3: VVX | CC3: VWAV | CD3: WWD | CE3: XTIA | CF3: YSS
A4: Agricultural Inputs | B4: {=TRANSPOSE(_xlfn._xlws.FILTER('stocks-list'!A4:A5546, 'stocks-list'!C4:C5546=A4, ""))} -> AVD | C4: BIOX | D4: CF | E4: CTVA | F4: FMC | G4: ICL | H4: IPI | I4: MOS | J4: NTR | K4: NXTS | L4: SEED | M4: SMG | N4: UAN
A5: Airlines | B5: {=TRANSPOSE(_xlfn._xlws.FILTER('stocks-list'!A5:A5547, 'stocks-list'!C5:C5547=A5, ""))} -> AAL | C5: AERO | D5: ALGT | E5: ALK | F5: CPA | G5: DAL | H5: FLYX | I5: JBLU | J5: LTM | K5: LUV | L5: RJET | M5: RYAAY | N5: SKYW | O5: SNCY | P5: SRFM | Q5: UAL | R5: ULCC | S5: VLRS
A6: Airports & Air Services | B6: {=TRANSPOSE(_xlfn._xlws.FILTER('stocks-list'!A6:A5548, 'stocks-list'!C6:C5548=A6, ""))} -> ASLE | C6: ASR | D6: CAAP | E6: JOBY | F6: OMAB | G6: PAC | H6: SOAR | I6: UP
A7: Aluminum | B7: {=TRANSPOSE(_xlfn._xlws.FILTER('stocks-list'!A7:A5549, 'stocks-list'!C7:C5549=A7, ""))} -> CENX | C7: CSTM | D7: KALU
A8: Apparel Manufacturing | B8: {=TRANSPOSE(_xlfn._xlws.FILTER('stocks-list'!A8:A5550, 'stocks-list'!C8:C5550=A8, ""))} -> COLM | C8: FIGS | D8: GIII | E8: GIL | F8: GOOS | G8: JL | H8: JRSH | I8: JXG | J8: KTB | K8: LAKE | L8: LEVI | M8: NCI | N8: OXM | O8: PLCE | P8: PMNT | Q8: PVH | R8: RL | S8: SGC | T8: UA | U8: UAA | V8: VFC | W8: VNCE | X8: XELB | Y8: ZGN
A9: Apparel Retail | B9: {=TRANSPOSE(_xlfn._xlws.FILTER('stocks-list'!A9:A5551, 'stocks-list'!C9:C5551=A9, ""))} -> AEO | C9: AKA | D9: ANF | E9: BIRD | F9: BKE | G9: BOOT | H9: BRIA | I9: BURL | J9: CAL | K9: CATO | L9: CRI | M9: CTRN | N9: CURV | O9: DLTH | P9: DXLG | Q9: GAP | R9: GCO | S9: JEM | T9: JILL | U9: LE | V9: LULU | W9: LVLU | X9: RENT | Y9: ROST | Z9: SCVL | AA9: SFIX | AB9: TJX | AC9: TLYS | AD9: URBN | AE9: VSCO | AF9: ZUMZ
A10: Asset Management | B10: {=TRANSPOSE(_xlfn._xlws.FILTER('stocks-list'!A10:A5552, 'stocks-list'!C10:C5552=A10, ""))} -> AAMI | C10: AB | D10: ALTI | E10: AMG | F10: AMP | G10: AMTD | H10: APAM | I10: APO | J10: ARCC | K10: ARES | L10: ASA | M10: ASST | N10: ATON | O10: AVX | P10: BAM | Q10: BBDC | R10: BCG | S10: BCIC | T10: BCSF | U10: BEN | V10: BENF | W10: BLK | X10: BN | Y10: BNBX | Z10: BNKK | AA10: BST | AB10: BTTC | AC10: BTX | AD10: BUR | AE10: BX | AF10: BXSL | AG10: CCAP | AH10: CET | AI10: CG | AJ10: CGBD | AK10: CION | AL10: CITR | AM10: CNS | AN10: CRBG | AO10: CSWC | AP10: CWD | AQ10: CYPH | AR10: DBRG | AS10: DFDV | AT10: DHIL | AU10: EARN | AV10: ECC | AW10: EIC | AX10: EQH | AY10: EQS | AZ10: FDUS | BA10: FGNX | BB10: FHI | BC10: FSK | BD10: GAIN | BE10: GBDC | BF10: GCMG | BG10: GECC | BH10: GEG | BI10: GLAD | BJ10: GROW | BK10: GSBD | BL10: HASI | BM10: HLNE | BN10: HNNA | BO10: HRZN | BP10: HSDT | BQ10: HTGC | BR10: ICMB | BS10: INV | BT10: IVZ | BU10: JHG | BV10: KBDC | BW10: KKR | BX10: LIEN | BY10: MAAS | BZ10: MAIN | CA10: MFIC | CB10: MGLD | CC10: MLCI | CD10: MRCC | CE10: MSDL | CF10: MSIF | CG10: NCDL | CH10: NMFC | CI10: NOAH | CJ10: NTRS | CK10: OBDC | CL10: OCSL | CM10: OFS | CN10: OIO | CO10: OTF | CP10: OWL | CQ10: OXSQ | CR10: PAX | CS10: PFG | CT10: PFLT | CU10: PFX | CV10: PNNT | CW10: PSBD | CX10: PSEC | CY10: RAND | CZ10: RJF | DA10: RMCO | DB10: RPC | DC10: RWAY | DD10: SAMG | DE10: SAR | DF10: SCM | DG10: SEIC | DH10: SII | DI10: SLRC | DJ10: SPMC | DK10: SSSS | DL10: STEP | DM10: STT | DN10: SWKH | DO10: TBLD | DP10: TCPC | DQ10: TGE | DR10: TPG | DS10: TPVG | DT10: TRIN | DU10: TROW | DV10: TSLX | DW10: TWAV | DX10: TYG | DY10: VCTR | DZ10: VINP | EA10: VRTS | EB10: WDAF | EC10: WHF | ED10: WHG | EE10: WT | EF10: WTF | EG10: ZSTK
A11: Asset Management - Income | B11: {=TRANSPOSE(_xlfn._xlws.FILTER('stocks-list'!A11:A5553, 'stocks-list'!C11:C5553=A11, ""))} -> DSL
A12: Auto & Truck Dealerships | B12: {=TRANSPOSE(_xlfn._xlws.FILTER('stocks-list'!A12:A5554, 'stocks-list'!C12:C5554=A12, ""))} -> ABG | C12: ACVA | D12: AN | E12: AZI | F12: BGSI | G12: CARG | H12: CRMT | I12: CVNA | J12: CWH | K12: DRVN | L12: GPI | M12: JZXN | N12: KFS | O12: KMX | P12: KXIN | Q12: LAD | R12: MCW | S12: OPLN | T12: OTH | U12: PAG | V12: RDNW | W12: RUSHA | X12: RUSHB | Y12: SAH | Z12: SDA | AA12: UCAR | AB12: UXIN | AC12: VVV
A13: Auto Manufacturers | B13: {=TRANSPOSE(_xlfn._xlws.FILTER('stocks-list'!A13:A5555, 'stocks-list'!C13:C5555=A13, ""))} -> AIIO | C13: CENN | D13: CYD | E13: DCX | F13: EMPD | G13: EVTV | H13: F | I13: FFAI | J13: FLYE | K13: GGR | L13: GM | M13: HMC | N13: LCID | O13: LI | P13: LOBO | Q13: LOT | R13: LVWR | S13: NIO | T13: NIU | U13: PSNY | V13: RACE | W13: RIVN | X13: SBLX | Y13: SEV | Z13: STLA | AA13: TM | AB13: TSLA | AC13: VFS | AD13: WKHS | AE13: XPEV
A14: Auto Parts | B14: {=TRANSPOSE(_xlfn._xlws.FILTER('stocks-list'!A14:A5556, 'stocks-list'!C14:C5556=A14, ""))} -> AAP | C14: ADNT | D14: ALSN | E14: ALV | F14: APTV | G14: ATMU | H14: AZO | I14: BWA | J14: CAAS | K14: CPS | L14: CVGI | M14: DAN | N14: DCH | O14: DORM | P14: ECX | Q14: FOXF | R14: FRSX | S14: GNTX | T14: GPC | U14: GT | V14: GTEC | W14: GTX | X14: HLLY | Y14: HSAI | Z14: HYLN | AA14: INEO | AB14: INVZ | AC14: LEA | AD14: LKQ | AE14: MBLY | AF14: MGA | AG14: MKDW | AH14: MLR | AI14: MNRO | AJ14: MOD | AK14: MPAA | AL14: MVST | AM14: ORLY | AN14: PHIN | AO14: PLOW | AP14: PRTS | AQ14: QS | AR14: REE | AS14: SES | AT14: SLDP | AU14: SMP | AV14: SRI | AW14: STRT | AX14: SYPR | AY14: THRM | AZ14: VC | BA14: VGNT | BB14: WKSP | BC14: WPRT | BD14: XPEL
A15: Banks - Diversified | B15: {=TRANSPOSE(_xlfn._xlws.FILTER('stocks-list'!A15:A5557, 'stocks-list'!C15:C5557=A15, ""))} -> BAC | C15: BBVA | D15: BCS | E15: BK | F15: BMO | G15: BNS | H15: C | I15: CM | J15: HSBC | K15: ING | L15: JPM | M15: MUFG | N15: NTB | O15: RY | P15: SAN | Q15: SMFG | R15: TD | S15: UBS | T15: WFC
A16: Banks - Regional | B16: {=TRANSPOSE(_xlfn._xlws.FILTER('stocks-list'!A16:A5558, 'stocks-list'!C16:C5558=A16, ""))} -> ABCB | C16: ACNB | D16: AFBI | E16: AGBK | F16: ALRS | G16: AMAL | H16: AMTB | I16: AROW | J16: ASB | K16: ASRV | L16: ATLO | M16: AUB | N16: AUBN | O16: AVAL | P16: AVBC | Q16: AVBH | R16: AX | S16: BAFN | T16: BANC | U16: BANF | V16: BANR | W16: BAP | X16: BBAR | Y16: BBD | Z16: BBDO | AA16: BBT | AB16: BCAL | AC16: BCBP | AD16: BCH | AE16: BCML | AF16: BFC | AG16: BFST | AH16: BHB | AI16: BHRB | AJ16: BKU | AK16: BLX | AL16: BMA | AM16: BMRC | AN16: BOH | AO16: BOKF | AP16: BOTJ | AQ16: BPOP | AR16: BPRN | AS16: BRBS | AT16: BSAC | AU16: BSBK | AV16: BSBR | AW16: BSRR | AX16: BSVN | AY16: BUSE | AZ16: BVFL | BA16: BWB | BB16: BWFG | BC16: BY | BD16: BYFC | BE16: CAC | BF16: CARE | BG16: CASH | BH16: CATY | BI16: CBAN | BJ16: CBC | BK16: CBFV | BL16: CBK | BM16: CBNA | BN16: CBNK | BO16: CBSH | BP16: CBU | BQ16: CCB | BR16: CCBG | BS16: CCNE | BT16: CFBK | BU16: CFFI | BV16: CFFN | BW16: CFG | BX16: CFR | BY16: CHCO | BZ16: CHMG | CA16: CIB | CB16: CIVB | CC16: CLBK | CD16: CLST | CE16: CNOB | CF16: COFS | CG16: COLB | CH16: COSO | CI16: CPBI | CJ16: CPF | CK16: CTBI | CL16: CUBI | CM16: CVBF | CN16: CWBC | CO16: CZFS | CP16: CZNC | CQ16: CZWI | CR16: DB | CS16: DCOM | CT16: EBC | CU16: EBMT | CV16: ECBK | CW16: EFSC | CX16: EFSI | CY16: EGBN | CZ16: EQBK | DA16: ESQ | DB16: EWBC | DC16: FBIZ | DD16: FBK | DE16: FBLA | DF16: FBNC | DG16: FBP | DH16: FCAP | DI16: FCBC | DJ16: FCCO | DK16: FCF | DL16: FCNCA | DM16: FDBC | DN16: FDSB | DO16: FFBC | DP16: FFIC | DQ16: FFIN | DR16: FGBI | DS16: FHB | DT16: FHN | DU16: FIBK | DV16: FINW | DW16: FISI | DX16: FITB | DY16: FLG | DZ16: FMAO | EA16: FMBH | EB16: FMNB | EC16: FNB | ED16: FNLC | EE16: FNWB | EF16: FNWD | EG16: FRAF | EH16: FRBA | EI16: FRME | EJ16: FRST | EK16: FSBC | EL16: FSBW | EM16: FSEA | EN16: FSUN | EO16: FULT | EP16: FUNC | EQ16: FUSB | ER16: FVCB | ES16: FXNC | ET16: GABC | EU16: GBCI | EV16: GBFH | EW16: GCBC | EX16: GGAL | EY16: GSBC | EZ16: HAFC | FA16: HBAN | FB16: HBCP | FC16: HBNC | FD16: HBT | FE16: HDB | FF16: HFBL | FG16: HFWA | FH16: HIFS | FI16: HNVR | FJ16: HOMB | FK16: HOPE | FL16: HTB | FM16: HTBK | FN16: HWBK | FO16: HWC | FP16: HYNE | FQ16: IBCP | FR16: IBN | FS16: IBOC | FT16: IFS | FU16: INBK | FV16: INDB | FW16: INTR | FX16: ISBA | FY16: ISTR | FZ16: ITUB | GA16: JMSB | GB16: KB | GC16: KEY | GD16: KFFB | GE16: KRNY | GF16: LARK | GG16: LC | GH16: LCNB | GI16: LKFN | GJ16: LNKB | GK16: LOB | GL16: LSBK | GM16: LYG | GN16: MBBC | GO16: MBIN | GP16: MBWM | GQ16: MCB | GR16: MCBS | GS16: MCHB | GT16: MFG | GU16: MGYR | GV16: MNSB | GW16: MPB | GX16: MRBK | GY16: MSBI | GZ16: MTB | HA16: MVBF | HB16: MYFW | HC16: NBBK | HD16: NBHC | HE16: NBN | HF16: NBTB | HG16: NECB | HH16: NEWT | HI16: NFBK | HJ16: NIC | HK16: NKSH | HL16: NPB | HM16: NRIM | HN16: NSTS | HO16: NU | HP16: NWBI | HQ16: NWFL | HR16: NWG | HS16: OBK | HT16: OBT | HU16: OCFC | HV16: OFG | HW16: ONB | HX16: OPBK | HY16: OPHC | HZ16: ORRF | IA16: OSBC | IB16: OVBC | IC16: OVLY | ID16: OZK | IE16: PB | IF16: PBFS | IG16: PBHC | IH16: PCB | II16: PDLB | IJ16: PEBK | IK16: PEBO | IL16: PFBC | IM16: PFIS | IN16: PFS | IO16: PGC | IP16: PKBK | IQ16: PLBC | IR16: PNBK | IS16: PNC | IT16: PNFP | IU16: PRK | IV16: PROV | IW16: QCRH | IX16: RBB | IY16: RBCAA | IZ16: RBKB | JA16: RF | JB16: RMBI | JC16: RNST | JD16: RRBI | JE16: RVSB | JF16: SBCF | JG16: SBFG | JH16: SBSI | JI16: SFBC | JJ16: SFBS | JK16: SFNC | JL16: SFST | JM16: SHBI | JN16: SHFS | JO16: SHG | JP16: SMBC | JQ16: SMBK | JR16: SPFI | JS16: SRBK | JT16: SRCE | JU16: SSB | JV16: SSBI | JW16: STBA | JX16: STEL | JY16: SUPV | JZ16: SYBT | KA16: TBBK | KB16: TCBI | KC16: TCBK | KD16: TCBS | KE16: TCBX | KF16: TFC | KG16: TFIN | KH16: TFSL | KI16: THFF | KJ16: TMP | KK16: TOWN | KL16: TRMK | KM16: TRST | KN16: TSBK | KO16: UBCP | KP16: UBSI | KQ16: UCB | KR16: UMBF | KS16: UNB | KT16: UNTY | KU16: USB | KV16: USCB | KW16: UVSP | KX16: VABK | KY16: VBNK | KZ16: VLY | LA16: WABC | LB16: WAFD | LC16: WAL | LD16: WASH | LE16: WBS | LF16: WF | LG16: WNEB | LH16: WSBC | LI16: WSBF | LJ16: WSBK | LK16: WSFS | LL16: WTBA | LM16: WTFC | LN16: ZION
A17: Beverages - Brewers | B17: {=TRANSPOSE(_xlfn._xlws.FILTER('stocks-list'!A17:A5559, 'stocks-list'!C17:C5559=A17, ""))} -> ABEV | C17: BUD | D17: CCU | E17: FMX | F17: SAM | G17: STZ | H17: TAP | I17: TAP.A
A18: Beverages - Non-Alcoholic | B18: {=TRANSPOSE(_xlfn._xlws.FILTER('stocks-list'!A18:A5560, 'stocks-list'!C18:C5560=A18, ""))} -> AKO.A | C18: AKO.B | D18: BRFH | E18: BUDA | F18: CCEP | G18: CELH | H18: COCO | I18: COKE | J18: FIZZ | K18: KDP | L18: KO | M18: KOF | N18: MNST | O18: PEP | P18: PRMB | Q18: REED | R18: STKL | S18: ZVIA
A19: Beverages - Wineries & Distilleries | B19: {=TRANSPOSE(_xlfn._xlws.FILTER('stocks-list'!A19:A5561, 'stocks-list'!C19:C5561=A19, ""))} -> AGCC | C19: BF.A | D19: BF.B | E19: DEO | F19: EPSM | G19: IBG | H19: MGPI | I19: SBEV | J19: SNDL | K19: WVVI | L19: YHC
A20: Biotechnology | B20: {=TRANSPOSE(_xlfn._xlws.FILTER('stocks-list'!A20:A5562, 'stocks-list'!C20:C5562=A20, ""))} -> ABCL | C20: ABEO | D20: ABOS | E20: ABSI | F20: ABUS | G20: ABVC | H20: ABVX | I20: ACAD | J20: ACET | K20: ACHV | L20: ACIU | M20: ACLX | N20: ACOG | O20: ACRS | P20: ACRV | Q20: ACTU | R20: ACXP | S20: ADAG | T20: ADCT | U20: ADIL | V20: ADMA | W20: ADPT | X20: ADTX | Y20: ADXN | Z20: AEON | AA20: AGEN | AB20: AGIO | AC20: AGMB | AD20: AIM | AE20: AKTS | AF20: AKTX | AG20: ALDX | AH20: ALEC | AI20: ALGS | AJ20: ALLO | AK20: ALLR | AL20: ALMS | AM20: ALNY | AN20: ALT | AO20: ALXO | AP20: ALZN | AQ20: ANAB | AR20: ANIX | AS20: ANL | AT20: ANNX | AU20: ANRO | AV20: ANTX | AW20: ANVS | AX20: APGE | AY20: APLM | AZ20: APLS | BA20: APM | BB20: APRE | BC20: APVO | BD20: ARCT | BE20: ARDX | BF20: ARGX | BG20: ARMP | BH20: ARQT | BI20: ARTL | BJ20: ARTV | BK20: ARVN | BL20: ARWR | BM20: ASBP | BN20: ASMB | BO20: ASND | BP20: ATAI | BQ20: ATHE | BR20: ATNM | BS20: ATOS | BT20: ATRA | BU20: ATYR | BV20: AUPH | BW20: AURA | BX20: AUTL | BY20: AVBP | BZ20: AVIR | CA20: AVTX | CB20: AVXL | CC20: AXSM | CD20: AZTR | CE20: BBIO | CF20: BBLG | CG20: BBOT | CH20: BCAB | CI20: BCAX | CJ20: BCDA | CK20: BCTX | CL20: BCYC | CM20: BDRX | CN20: BDTX | CO20: BEAM | CP20: BGMS | CQ20: BHVN | CR20: BIVI | CS20: BLRX | CT20: BLTE | CU20: BMEA | CV20: BMRN | CW20: BNTC | CX20: BNTX | CY20: BOLD | CZ20: BOLT | DA20: BRNS | DB20: BRTX | DC20: BYSI | DD20: CABA | DE20: CADL | DF20: CAI | DG20: CALC | DH20: CAMP | DI20: CANF | DJ20: CAPR | DK20: CBIO | DL20: CBUS | DM20: CCCC | DN20: CDIO | DO20: CDT | DP20: CDXS | DQ20: CELC | DR20: CELU | DS20: CELZ | DT20: CGEM | DU20: CGEN | DV20: CGON | DW20: CGTX | DX20: CHRS | DY20: CING | DZ20: CLDI | EA20: CLDX | EB20: CLGN | EC20: CLLS | ED20: CLRB | EE20: CLYM | EF20: CMMB | EG20: CMND | EH20: CMPX | EI20: CNSP | EJ20: CNTA | EK20: CNTB | EL20: CNTN | EM20: CNTX | EN20: COCP | EO20: COEP | EP20: COGT | EQ20: CORT | ER20: COYA | ES20: CPRX | ET20: CRBP | EU20: CRBU | EV20: CRDF | EW20: CRIS | EX20: CRMD | EY20: CRNX | EZ20: CRSP | FA20: CRVO | FB20: CRVS | FC20: CSBR | FD20: CTMX | FE20: CTNM | FF20: CTXR | FG20: CUE | FH20: CVKD | FI20: CVM | FJ20: CYCN | FK20: CYTK | FL20: DARE | FM20: DAWN | FN20: DBVT | FO20: DCOY | FP20: DFTX | FQ20: DMAC | FR20: DMRA | FS20: DNA | FT20: DNLI | FU20: DNTH | FV20: DRMA | FW20: DRTS | FX20: DRUG | FY20: DSGN | FZ20: DTIL | GA20: DWTX | GB20: DYAI | GC20: DYN | GD20: EDIT | GE20: EDSA | GF20: EIKN | GG20: ELAB | GH20: ELDN | GI20: ELTX | GJ20: ELVN | GK20: ENGN | GL20: ENLV | GM20: ENSC | GN20: ENTA | GO20: ENTX | GP20: ENVB | GQ20: EPRX | GR20: EQ | GS20: ERAS | GT20: ERNA | GU20: ESLA | GV20: EVAX | GW20: EVGN | GX20: EVMN | GY20: EWTX | GZ20: EXEL | HA20: EXOZ | HB20: EYPT | HC20: FATE | HD20: FBIO | HE20: FBLG | HF20: FBRX | HG20: FDMT | HH20: FENC | HI20: FHTX | HJ20: FLNA | HK20: FOLD | HL20: FTRE | HM20: FULC | HN20: GALT | HO20: GANX | HP20: GDTC | HQ20: GENB | HR20: GERN | HS20: GHRS | HT20: GLMD | HU20: GLPG | HV20: GLSI | HW20: GLUE | HX20: GMAB | HY20: GNLX | HZ20: GNPX | IA20: GNTA | IB20: GOSS | IC20: GOVX | ID20: GPCR | IE20: GRCE | IF20: GRDX | IG20: GRI | IH20: GTBP | II20: GUTS | IJ20: GYRE | IK20: HALO | IL20: HCWB | IM20: HELP | IN20: HIND | IO20: HOTH | IP20: HOWL | IQ20: HRMY | IR20: HRTX | IS20: HUMA | IT20: HURA | IU20: HYFT | IV20: HYPD | IW20: IBIO | IX20: IBO | IY20: IBRX | IZ20: ICCC | JA20: ICU | JB20: IDYA | JC20: IFRX | JD20: IGC | JE20: IKT | JF20: IMA | JG20: IMCR | JH20: IMMP | JI20: IMMX | JJ20: IMNM | JK20: IMNN | JL20: IMRN | JM20: IMRX | JN20: IMTX | JO20: IMUX | JP20: IMVT | JQ20: INAB | JR20: INBX | JS20: INCY | JT20: INDP | JU20: INKT | JV20: INMB | JW20: INO | JX20: INSM | JY20: INTS | JZ20: INVA | KA20: IOBT | KB20: IONS | KC20: IOVA | KD20: IPHA | KE20: IPSC | KF20: IRD | KG20: IRON | KH20: IVA | KI20: IVVD | KJ20: JAGX | KK20: JANX | KL20: JAZZ | KM20: JBIO | KN20: JSPR | KO20: JUNS | KP20: KALA | KQ20: KALV | KR20: KAPA | KS20: KLRS | KT20: KOD | KU20: KPRX | KV20: KPTI | KW20: KROS | KX20: KRRO | KY20: KRYS | KZ20: KTTA | LA20: KURA | LB20: KYMR | LC20: KYNB | LD20: KYTX | LE20: KZIA | LF20: KZR | LG20: LBRX | LH20: LCTX | LI20: LEGN | LJ20: LENZ | LK20: LEXX | LL20: LGND | LM20: LGVN | LN20: LIMN | LO20: LITS | LP20: LIXT | LQ20: LNAI | LR20: LONA | LS20: LPCN | LT20: LRMR | LU20: LSTA | LV20: LTRN | LW20: LXEO | LX20: LXRX | LY20: LYEL | LZ20: MAIA | MA20: MANE | MB20: MAZE | MC20: MBIO | MD20: MBRX | ME20: MBX | MF20: MCRB | MG20: MDGL | MH20: MDWD | MI20: MDXG | MJ20: MENS | MK20: MESO | ML20: MGNX | MM20: MGTX | MN20: MGX | MO20: MIRM | MP20: MIST | MQ20: MLEC | MR20: MLTX | MS20: MLYS | MT20: MNKD | MU20: MNOV | MV20: MNPR | MW20: MOLN | MX20: MPLT | MY20: MREO | MZ20: MRKR | NA20: MRNA | NB20: MRVI | NC20: MTNB | ND20: MTVA | NE20: NAGE | NF20: NAMS | NG20: NAUT | NH20: NBP | NI20: NBTX | NJ20: NCEL | NK20: NCNA | NL20: NERV | NM20: NEUP | NN20: NGEN | NO20: NGNE | NP20: NKTR | NQ20: NKTX | NR20: NMRA | NS20: NNVC | NT20: NRIX | NU20: NRSN | NV20: NRXP | NW20: NRXS | NX20: NTHI | NY20: NTLA | NZ20: NTRB | OA20: NUVB | OB20: NUVL | OC20: NVAX | OD20: NVCT | OE20: NXTC | OF20: OABI | OG20: OBIO | OH20: OCGN | OI20: OCS | OJ20: OCUL | OK20: OGEN | OL20: OKUR | OM20: OKYO | ON20: OLMA | OO20: OMER | OP20: ONC | OQ20: ONCO | OR20: ONCY | OS20: ORIC | OT20: ORKA | OU20: ORMP | OV20: OSRH | OW20: OSTX | OX20: OTLK | OY20: OVID | OZ20: PALI | PA20: PASG | PB20: PBM | PC20: PBYI | PD20: PCSA | PE20: PCVX | PF20: PDSB | PG20: PEPG | PH20: PGEN | PI20: PHAR | PJ20: PHAT | PK20: PHGE | PL20: PHIO | PM20: PHVS | PN20: PLRX | PO20: PLRZ | PP20: PLUR | PQ20: PLX | PR20: PLYX | PS20: PMCB | PT20: PMN | PU20: PMVP | PV20: PPBT | PW20: PPCB | PX20: PRAX | PY20: PRLD | PZ20: PRME | QA20: PROK | QB20: PRQR | QC20: PRTA | QD20: PRTC | QE20: PSTV | QF20: PTCT | QG20: PTGX | QH20: PTHS | QI20: PTN | QJ20: PULM | QK20: PVLA | QL20: PYPD | QM20: PYXS | QN20: QNCX | QO20: QNRX | QP20: QNTM | QQ20: QTTB | QR20: QURE | QS20: RADX | QT20: RANI | QU20: RAPP | QV20: RARE | QW20: RCKT | QX20: RCUS | QY20: REGN | QZ20: REPL | RA20: REVB | RB20: RGNX | RC20: RIGL | RD20: RLAY | RE20: RLMD | RF20: RLYB | RG20: RNAC | RH20: RNAZ | RI20: RNTX | RJ20: RNXT | RK20: ROIV | RL20: RPRX | RM20: RVMD | RN20: RVPH | RO20: RXRX | RP20: RYTM | RQ20: RZLT | RR20: SABS | RS20: SANA | RT20: SCNI | RU20: SEER | RV20: SEPN | RW20: SER | RX20: SGMO | RY20: SGMT | RZ20: SGP | SA20: SILO | SB20: SION | SC20: SKYE | SD20: SLDB | SE20: SLGL | SF20: SLN | SG20: SLNO | SH20: SLS | SI20: SLXN | SJ20: SMMT | SK20: SNDX | SL20: SNGX | SM20: SNSE | SN20: SNTI | SO20: SPRB | SP20: SPRC | SQ20: SPRO | SR20: SPRY | SS20: SRPT | ST20: SRRK | SU20: SRZN | SV20: STOK | SW20: STRO | SX20: STTK | SY20: SVRA | SZ20: SXTP | TA20: SYRE | TB20: TARA | TC20: TARS | TD20: TBPH | TE20: TCRT | TF20: TCRX | TG20: TECH | TH20: TECX | TI20: TELO | TJ20: TENX | TK20: TERN | TL20: TGTX | TM20: TIL | TN20: TLSA | TO20: TLX | TP20: TNGX | TQ20: TNXP | TR20: TNYA | TS20: TOVX | TT20: TPST | TU20: TRAW | TV20: TRDA | TW20: TRVI | TX20: TSHA | TY20: TTRX | TZ20: TVGN | UA20: TVRD | UB20: TVTX | UC20: TYRA | UD20: UNCY | UE20: UPB | UF20: URGN | UG20: VALN | UH20: VANI | UI20: VCEL | UJ20: VERA | UK20: VERU | UL20: VIR | UM20: VIVS | UN20: VKTX | UO20: VNDA | UP20: VOR | UQ20: VRAX | UR20: VRCA | US20: VRDN | UT20: VRTX | UU20: VSTM | UV20: VTGN | UW20: VTVT | UX20: VYGR | UY20: VYNE | UZ20: WHWK | VA20: WVE | VB20: XBIO | VC20: XBIT | VD20: XCUR | VE20: XENE | VF20: XERS | VG20: XFOR | VH20: XLO | VI20: XNCR | VJ20: XOMA | VK20: XTLB | VL20: YDES | VM20: ZBIO | VN20: ZLAB | VO20: ZNTL | VP20: ZURA | VQ20: ZVRA | VR20: ZYME
A21: Blockchain | B21: {=TRANSPOSE(_xlfn._xlws.FILTER('stocks-list'!A21:A5563, 'stocks-list'!C21:C5563=A21, ""))} -> AIB
A22: Broadcasting | B22: {=TRANSPOSE(_xlfn._xlws.FILTER('stocks-list'!A22:A5564, 'stocks-list'!C22:C5564=A22, ""))} -> BBGI | C22: CURI | D22: FUBO | E22: GTN | F22: GTN.A | G22: IHRT | H22: MDIA | I22: NMAX | J22: NXST | K22: SBGI | L22: SGA | M22: SSP | N22: UONE | O22: UONEK | P22: XHLD
A23: Building Materials | B23: {=TRANSPOSE(_xlfn._xlws.FILTER('stocks-list'!A23:A5565, 'stocks-list'!C23:C5565=A23, ""))} -> AMRZ | C23: CAPS | D23: CAPT | E23: CPAC | F23: CRH | G23: CX | H23: EXP | I23: JHX | J23: KNF | K23: LOMA | L23: MLM | M23: RETO | N23: SMID | O23: TGLS | P23: TTAM | Q23: USLM | R23: VMC
A24: Building Products & Equipment | B24: {=TRANSPOSE(_xlfn._xlws.FILTER('stocks-list'!A24:A5566, 'stocks-list'!C24:C5566=A24, ""))} -> AEHL | C24: AIRJ | D24: APOG | E24: APT | F24: ARLO | G24: ASPN | H24: AWI | I24: BLDR | J24: CARR | K24: CSL | L24: CSTE | M24: FBIN | N24: GCDT | O24: GFF | P24: ILAG | Q24: INVE | R24: JBI | S24: JCI | T24: JELD | U24: JLHL | V24: LII | W24: LMB | X24: LPX | Y24: MAS | Z24: NX | AA24: OC | AB24: PPIH | AC24: ROCK | AD24: SPXC | AE24: SWIM | AF24: TREX | AG24: TT | AH24: UUU | AI24: WMS
A25: Business Equipment & Supplies | B25: {=TRANSPOSE(_xlfn._xlws.FILTER('stocks-list'!A25:A5567, 'stocks-list'!C25:C5567=A25, ""))} -> ACCO | C25: ACTG | D25: EBF | E25: EHGO | F25: XRX
A26: Capital Markets | B26: {=TRANSPOSE(_xlfn._xlws.FILTER('stocks-list'!A26:A5568, 'stocks-list'!C26:C5568=A26, ""))} -> ABTC | C26: ABTS | D26: ANY | E26: ARBK | F26: ATCH | G26: AURE | H26: AXG | I26: BGC | J26: BMHL | K26: BMNR | L26: BRBI | M26: BRR | N26: BTBT | O26: BTCS | P26: BTM | Q26: CANG | R26: CD | S26: CLSK | T26: CNCK | U26: COHN | V26: CRCL | W26: DEFT | X26: DOMH | Y26: ETOR | Z26: EVR | AA26: FIGR | AB26: FLD | AC26: FUFU | AD26: FUTU | AE26: GEMI | AF26: GLXY | AG26: GOLD | AH26: GRAN | AI26: GREE | AJ26: GS | AK26: GSIW | AL26: HGBL | AM26: HIVE | AN26: HLI | AO26: HOOD | AP26: HUT | AQ26: IBKR | AR26: IPST | AS26: IREN | AT26: JEF | AU26: LAZ | AV26: LGHL | AW26: LMFA | AX26: LPLA | AY26: MARA | AZ26: MATH | BA26: MC | BB26: MDBH | BC26: MEGL | BD26: MIAX | BE26: MIGI | BF26: MKTX | BG26: MRX | BH26: MS | BI26: NAKA | BJ26: NCPL | BK26: NCTY | BL26: NMR | BM26: OPY | BN26: PIPR | BO26: PJT | BP26: PLUT | BQ26: PURR | BR26: PWP | BS26: RIOT | BT26: SBET | BU26: SCHW | BV26: SF | BW26: SIEB | BX26: SLNH | BY26: SNEX | BZ26: SOS | CA26: SRL | CB26: STEX | CC26: STKE | CD26: TIGR | CE26: TOP | CF26: TW | CG26: VIRT | CH26: WAI | CI26: WULF | CJ26: XP | CK26: ZBAI
A27: Chemicals | B27: {=TRANSPOSE(_xlfn._xlws.FILTER('stocks-list'!A27:A5569, 'stocks-list'!C27:C5569=A27, ""))} -> ACNT | C27: ASIX | D27: ASPI | E27: BAK | F27: CE | G27: DOW | H27: GPRE | I27: GURE | J27: HUN | K27: LXU | L27: MEOH | M27: OLN | N27: ORGN | O27: REX | P27: RYAM | Q27: TROX | R27: VHI | S27: WLKP
A28: Coking Coal | B28: {=TRANSPOSE(_xlfn._xlws.FILTER('stocks-list'!A28:A5570, 'stocks-list'!C28:C5570=A28, ""))} -> AMR | C28: AREC | D28: HCC | E28: METC | F28: METCB | G28: SXC
A29: Communication Equipment | B29: {=TRANSPOSE(_xlfn._xlws.FILTER('stocks-list'!A29:A5571, 'stocks-list'!C29:C5571=A29, ""))} -> ADTN | C29: AIRG | D29: AMPG | E29: ASNS | F29: ASTS | G29: AUDC | H29: AVNW | I29: BDC | J29: BKTI | K29: BOSC | L29: CIEN | M29: CLFD | N29: CLRO | O29: CMTL | P29: CRNT | Q29: CSCO | R29: DGII | S29: ERIC | T29: EXTR | U29: FEIM | V29: FIEE | W29: FKWL | X29: GILT | Y29: HLIT | Z29: HPE | AA29: INSG | AB29: LITE | AC29: LTRX | AD29: MITQ | AE29: MSI | AF29: NOK | AG29: NTGR | AH29: OCC | AI29: ONDS | AJ29: SILC | AK29: SYNX | AL29: TSAT | AM29: UI | AN29: UTSI | AO29: VIAV | AP29: VISN | AQ29: VSAT | AR29: WATT | AS29: ZBRA
A30: Computer Hardware | B30: {=TRANSPOSE(_xlfn._xlws.FILTER('stocks-list'!A30:A5572, 'stocks-list'!C30:C5572=A30, ""))} -> AGMH | C30: ALOT | D30: AMCI | E30: ANET | F30: BGIN | G30: BTCT | H30: CAN | I30: CRCT | J30: CRSR | K30: DDD | L30: DELL | M30: DPRO | N30: EBON | O30: HPQ | P30: IONQ | Q30: KTCC | R30: LOGI | S30: MCRP | T30: NNDM | U30: OSS | V30: PSTG | W30: QBTS | X30: QCLS | Y30: QMCO | Z30: QUBT | AA30: RGTI | AB30: SCKT | AC30: SMCI | AD30: SNDK | AE30: SSYS | AF30: STX | AG30: TACT | AH30: UAVS | AI30: UMAC | AJ30: VELO | AK30: VTIX | AL30: WDC | AM30: YIBO | AN30: ZSPC
A31: Confectioners | B31: {=TRANSPOSE(_xlfn._xlws.FILTER('stocks-list'!A31:A5573, 'stocks-list'!C31:C5573=A31, ""))} -> HSY | C31: MDLZ | D31: RMCF | E31: SOWG | F31: TR
A32: Conglomerates | B32: {=TRANSPOSE(_xlfn._xlws.FILTER('stocks-list'!A32:A5574, 'stocks-list'!C32:C5574=A32, ""))} -> AIRT | C32: BBUC | D32: BOC | E32: BOOM | F32: CODI | G32: CRESY | H32: DLX | I32: FBYD | J32: FIP | K32: HHS | L32: HON | M32: LGPS | N32: MAMK | O32: MATW | P32: MMM | Q32: NNBR | R32: OTTR | S32: PAM | T32: PLAG | U32: RCMT | V32: SEB | W32: STRR | X32: TRC | Y32: TTI | Z32: TUSK | AA32: VMI
A33: Consulting Services | B33: {=TRANSPOSE(_xlfn._xlws.FILTER('stocks-list'!A33:A5575, 'stocks-list'!C33:C5575=A33, ""))} -> ACCL | C33: AERT | D33: BAH | E33: CRAI | F33: DGNX | G33: EFTY | H33: EFX | I33: EGG | J33: FCN | K33: FOFO | L33: FORR | M33: GRNQ | N33: HURN | O33: ICFI | P33: INTJ | Q33: LAWR | R33: RGP | S33: ROMA | T33: RYOJ | U33: SBC | V33: VCIG | W33: VRSK | X33: ZGM
A34: Consumer Electronics | B34: {=TRANSPOSE(_xlfn._xlws.FILTER('stocks-list'!A34:A5576, 'stocks-list'!C34:C5576=A34, ""))} -> AXIL | C34: BOXL | D34: FEBO | E34: FOXX | F34: GMEX | G34: GPRO | H34: KOSS | I34: LPL | J34: MSN | K34: RIME | L34: SONO | M34: SONY | N34: TBCH | O34: UEIC | P34: VUZI | Q34: WLDS | R34: WTO | S34: ZEPP
A35: Copper | B35: {=TRANSPOSE(_xlfn._xlws.FILTER('stocks-list'!A35:A5577, 'stocks-list'!C35:C5577=A35, ""))} -> ERO | C35: FCX | D35: HBM | E35: IE | F35: SCCO | G35: TGB
A36: Credit Services | B36: {=TRANSPOSE(_xlfn._xlws.FILTER('stocks-list'!A36:A5578, 'stocks-list'!C36:C5578=A36, ""))} -> AFRM | C36: AGM | D36: AGM.A | E36: ALLY | F36: ANTA | G36: ATLC | H36: AXP | I36: BFH | J36: CACC | K36: COF | L36: CPSS | M36: DXF | N36: ECPG | O36: ENVA | P36: EZPW | Q36: FCFS | R36: FINV | S36: FOA | T36: GDOT | U36: HTT | V36: JCAP | W36: JF | X36: LPRO | Y36: LU | Z36: LX | AA36: MA | AB36: MFIN | AC36: NAVI | AD36: NNI | AE36: OMF | AF36: OPFI | AG36: OPRT | AH36: PAYP | AI36: PICS | AJ36: PMTS | AK36: PRAA | AL36: PYPL | AM36: QFIN | AN36: RM | AO36: SEZL | AP36: SLM | AQ36: SNTG | AR36: SOFI | AS36: SUIG | AT36: SYF | AU36: TROO | AV36: UPST | AW36: V | AX36: WRLD | AY36: WU | AZ36: XYF | BA36: YRD
A37: Department Stores | B37: {=TRANSPOSE(_xlfn._xlws.FILTER('stocks-list'!A37:A5579, 'stocks-list'!C37:C5579=A37, ""))} -> DDS | C37: KSS | D37: M | E37: PLBL
A38: Diagnostics & Research | B38: {=TRANSPOSE(_xlfn._xlws.FILTER('stocks-list'!A38:A5580, 'stocks-list'!C38:C5580=A38, ""))} -> ADVB | C38: BDSX | D38: BIAF | E38: BLLN | F38: BNR | G38: CDNA | H38: CRL | I38: CSTL | J38: DGX | K38: DHR | L38: FLGT | M38: FONR | N38: GH | O38: GRAL | P38: ICLR | Q38: IDXX | R38: ILMN | S38: IMDX | T38: IQV | U38: ISPC | V38: LH | W38: MBAI | X38: MDXH | Y38: MEDP | Z38: MTD | AA38: MYGN | AB38: NDRA | AC38: NEO | AD38: NOTV | AE38: NTRA | AF38: OPK | AG38: PRE | AH38: PRPO | AI38: PSNL | AJ38: QGEN | AK38: QUCY | AL38: RDNT | AM38: RVTY | AN38: SHC | AO38: TMO | AP38: TWST | AQ38: VCYT | AR38: WAT | AS38: WGS | AT38: XGN | AU38: XWEL
A39: Discount Stores | B39: {=TRANSPOSE(_xlfn._xlws.FILTER('stocks-list'!A39:A5581, 'stocks-list'!C39:C5581=A39, ""))} -> BJ | C39: COST | D39: DG | E39: DLTR | F39: OLLI | G39: PSMT | H39: TBBB | I39: TGT | J39: WMT
A40: Drug Manufacturers - General | B40: {=TRANSPOSE(_xlfn._xlws.FILTER('stocks-list'!A40:A5582, 'stocks-list'!C40:C5582=A40, ""))} -> AMGN | C40: AMRN | D40: AZN | E40: BIIB | F40: BMY | G40: GILD | H40: GRFS | I40: GSK | J40: JNJ | K40: LLY | L40: MDCX | M40: MIRA | N40: MRK | O40: NSRX | P40: NVO | Q40: NVS | R40: OGN | S40: PFE | T40: SCLX | U40: SNY
A41: Drug Manufacturers - Specialty & Generic | B41: {=TRANSPOSE(_xlfn._xlws.FILTER('stocks-list'!A41:A5583, 'stocks-list'!C41:C5583=A41, ""))} -> ACB | C41: AKAN | D41: AKBA | E41: ALKS | F41: ALVO | G41: AMLX | H41: AMPH | I41: AMRX | J41: ANIK | K41: ANIP | L41: APUS | M41: AQST | N41: ASRT | O41: AYTU | P41: BCRX | Q41: BFRI | R41: BGM | S41: BHC | T41: BIOA | U41: BTAI | V41: CABR | W41: CGC | X41: COLL | Y41: CPHI | Z41: CPIX | AA41: CRDL | AB41: CRON | AC41: CTOR | AD41: DERM | AE41: EBS | AF41: ELAN | AG41: EOLS | AH41: ESPR | AI41: ETON | AJ41: EVO | AK41: GELS | AL41: HCM | AM41: HIMS | AN41: HLN | AO41: HROW | AP41: IMCC | AQ41: INCR | AR41: INM | AS41: IRWD | AT41: IXHL | AU41: KMDA | AV41: KNSA | AW41: LFCR | AX41: LNTH | AY41: LQDA | AZ41: NBIX | BA41: OGI | BB41: ORGO | BC41: PAHC | BD41: PBH | BE41: PCRX | BF41: PRFX | BG41: PRGO | BH41: RDHL | BI41: RDY | BJ41: RGC | BK41: RMTI | BL41: SBFM | BM41: SCYX | BN41: SHPH | BO41: SIGA | BP41: SNOA | BQ41: SUPN | BR41: SXTC | BS41: TAK | BT41: TEVA | BU41: TKNO | BV41: TLPH | BW41: TLRY | BX41: TXMD | BY41: UPC | BZ41: UTHR | CA41: VTRS | CB41: YCBD | CC41: ZTS | CD41: ZYBT
A42: Education & Training Services | B42: {=TRANSPOSE(_xlfn._xlws.FILTER('stocks-list'!A42:A5584, 'stocks-list'!C42:C5584=A42, ""))} -> AFYA | C42: AMBO | D42: APEI | E42: CHGG | F42: COE | G42: COUR | H42: CVSA | I42: DAO | J42: EDTK | K42: EDU | L42: EEIQ | M42: FC | N42: FCHL | O42: FEDU | P42: GHC | Q42: GNS | R42: GOTU | S42: GSUN | T42: GV | U42: IH | V42: KIDZ | W42: KLC | X42: LAUR | Y42: LGCY | Z42: LINC | AA42: LOPE | AB42: LRN | AC42: LXEH | AD42: MH | AE42: MYND | AF42: PRDO | AG42: PXED | AH42: RYET | AI42: SKIL | AJ42: STG | AK42: STRA | AL42: TAL | AM42: UDMY | AN42: UTI | AO42: VSA | AP42: WAFU | AQ42: YOUL | AR42: YQ
A43: Electrical Equipment & Parts | B43: {=TRANSPOSE(_xlfn._xlws.FILTER('stocks-list'!A43:A5585, 'stocks-list'!C43:C5585=A43, ""))} -> ADSE | C43: AEIS | D43: AMPX | E43: APWC | F43: ATKR | G43: AYI | H43: BE | I43: BLDP | J43: CBAT | K43: CCTG | L43: DFLI | M43: EAF | N43: ELPW | O43: ELVA | P43: ENR | Q43: ENS | R43: ENVX | S43: EOSE | T43: EPOW | U43: ESP | V43: FCEL | W43: FLUX | X43: GWH | Y43: HAYW | Z43: HUBB | AA43: KE | AB43: LNKS | AC43: LTBR | AD43: NEOV | AE43: NVT | AF43: NVX | AG43: OESX | AH43: PLPC | AI43: PLUG | AJ43: POLA | AK43: POWL | AL43: PPSI | AM43: RAYA | AN43: RFIL | AO43: SDST | AP43: SKYX | AQ43: STI | AR43: TE | AS43: TGEN | AT43: ULBI | AU43: VRT | AV43: XPON
A44: Electronic Components | B44: {=TRANSPOSE(_xlfn._xlws.FILTER('stocks-list'!A44:A5586, 'stocks-list'!C44:C5586=A44, ""))} -> ALNT | C44: APH | D44: BELFA | E44: BELFB | F44: BHE | G44: CLS | H44: CPSH | I44: CTS | J44: DAIO | K44: DAKT | L44: DSWL | M44: ELTK | N44: FLEX | O44: FN | P44: FPS | Q44: GAUZ | R44: GLW | S44: HOLO | T44: IMTE | U44: JBL | V44: KN | W44: KOPN | X44: KULR | Y44: LFUS | Z44: LINK | AA44: LPTH | AB44: LYTS | AC44: MEI | AD44: MPTI | AE44: MTEK | AF44: NEON | AG44: OLED | AH44: OPTX | AI44: OSIS | AJ44: OST | AK44: OUST | AL44: PLXS | AM44: RAL | AN44: REFR | AO44: RELL | AP44: ROG | AQ44: SANM | AR44: SELX | AS44: TEL | AT44: TTMI | AU44: VICR | AV44: WBX | AW44: WETH
A45: Electronic Gaming & Multimedia | B45: {=TRANSPOSE(_xlfn._xlws.FILTER('stocks-list'!A45:A5587, 'stocks-list'!C45:C5587=A45, ""))} -> CTW | C45: DDI | D45: DKI | E45: EA | F45: GAME | G45: GCL | H45: GDC | I45: GDEV | J45: GIGM | K45: GMHS | L45: GRVY | M45: GXAI | N45: MRDN | O45: MSGM | P45: MYPS | Q45: NTES | R45: PLTK | S45: RBLX | T45: SKLZ | U45: SNAL | V45: SOHU | W45: TBH | X45: TTWO
A46: Electronics & Computer Distribution | B46: {=TRANSPOSE(_xlfn._xlws.FILTER('stocks-list'!A46:A5588, 'stocks-list'!C46:C5588=A46, ""))} -> ARW | C46: AVT | D46: CLMB | E46: CNXN | F46: IZM | G46: NSIT | H46: SCSC | I46: SNX
A47: Engineering & Construction | B47: {=TRANSPOSE(_xlfn._xlws.FILTER('stocks-list'!A47:A5589, 'stocks-list'!C47:C5589=A47, ""))} -> ACM | C47: AGX | D47: AMRC | E47: APG | F47: ATCX | G47: BBCP | H47: BLD | I47: BLNK | J47: BWMN | K47: CDLR | L47: CDNL | M47: DY | N47: ECG | O47: EME | P47: ESOA | Q47: EXPO | R47: FBGL | S47: FER | T47: FGL | U47: FIX | V47: FLR | W47: GVA | X47: IESC | Y47: J | Z47: KBR | AA47: LGN | AB47: MAGH | AC47: MGN | AD47: MIMI | AE47: MSGY | AF47: MSW | AG47: MTRX | AH47: MTZ | AI47: MYRG | AJ47: OFAL | AK47: ONEG | AL47: ORN | AM47: PHOE | AN47: PRIM | AO47: PWR | AP47: RITR | AQ47: ROAD | AR47: SHIM | AS47: SKBL | AT47: SKK | AU47: SLND | AV47: STN | AW47: STRL | AX47: TPC | AY47: TTEK | AZ47: VATE | BA47: WLDN | BB47: ZDAI
A48: Entertainment | B48: {=TRANSPOSE(_xlfn._xlws.FILTER('stocks-list'!A48:A5590, 'stocks-list'!C48:C5590=A48, ""))} -> AENT | C48: AGAE | D48: AMC | E48: AMCX | F48: ANGH | G48: ANGX | H48: BATRA | I48: BATRK | J48: CNK | K48: CNVS | L48: CPOP | M48: DIS | N48: FOX | O48: FOXA | P48: FTRK | Q48: FWONA | R48: FWONK | S48: GAIA | T48: HUYA | U48: IMAX | V48: IQ | W48: KUST | X48: KWM | Y48: LFS | Z48: LION | AA48: LLYVA | AB48: LLYVK | AC48: LVO | AD48: LYV | AE48: MANU | AF48: MCS | AG48: MPU | AH48: MSGS | AI48: NFLX | AJ48: NIPG | AK48: NWS | AL48: NWSA | AM48: PLAY | AN48: PSKY | AO48: RDI | AP48: RDIB | AQ48: ROKU | AR48: RSVR | AS48: SIRI | AT48: SLMT | AU48: SPHR | AV48: STRZ | AW48: TKO | AX48: TOON | AY48: VSNT | AZ48: WBD | BA48: WMG | BB48: ZNB
A49: Farm & Heavy Construction Machinery | B49: {=TRANSPOSE(_xlfn._xlws.FILTER('stocks-list'!A49:A5591, 'stocks-list'!C49:C5591=A49, ""))} -> AEBI | C49: AGCO | D49: ALG | E49: ARTW | F49: ASTE | G49: BLBD | H49: BNC | I49: CAT | J49: CMCO | K49: CNH | L49: DE | M49: GENC | N49: GP | O49: HCAI | P49: HY | Q49: HYFM | R49: LNN | S49: MTW | T49: OSK | U49: PCAR | V49: SCAG | W49: TEX | X49: TWI | Y49: UGRO | Z49: WNC | AA49: XOS
A50: Farm Products | B50: {=TRANSPOSE(_xlfn._xlws.FILTER('stocks-list'!A50:A5592, 'stocks-list'!C50:C5592=A50, ""))} -> ADM | C50: AFRI | D50: AGRO | E50: AGRZ | F50: ALCO | G50: AQB | H50: BG | I50: CALM | J50: DOLE | K50: EDBL | L50: FDP | M50: LMNR | N50: LND | O50: LOCL | P50: PFAI | Q50: SDOT | R50: TSN | S50: VFF | T50: VITL
A51: Financial - Capital Markets | B51: {=TRANSPOSE(_xlfn._xlws.FILTER('stocks-list'!A51:A5593, 'stocks-list'!C51:C5593=A51, ""))} -> KEEL
A52: Financial Conglomerates | B52: {=TRANSPOSE(_xlfn._xlws.FILTER('stocks-list'!A52:A5594, 'stocks-list'!C52:C5594=A52, ""))} -> FRHC | C52: HTH | D52: IX | E52: RILY | F52: TREE | G52: VOYA
A53: Financial Data & Stock Exchanges | B53: {=TRANSPOSE(_xlfn._xlws.FILTER('stocks-list'!A53:A5595, 'stocks-list'!C53:C5595=A53, ""))} -> BTOG | C53: CBOE | D53: CME | E53: COIN | F53: CSHR | G53: DTCX | H53: FDS | I53: ICE | J53: MCO | K53: MKTW | L53: MORN | M53: MSCI | N53: NDAQ | O53: SPGI | P53: TRU | Q53: VALU
A54: Food Distribution | B54: {=TRANSPOSE(_xlfn._xlws.FILTER('stocks-list'!A54:A5596, 'stocks-list'!C54:C5596=A54, ""))} -> ANDE | C54: AVO | D54: CHEF | E54: CVGW | F54: DIT | G54: HFFG | H54: MTEX | I54: PFGC | J54: SYY | K54: TWG | L54: UNFI | M54: USFD | N54: WILC
A55: Footwear & Accessories | B55: {=TRANSPOSE(_xlfn._xlws.FILTER('stocks-list'!A55:A5597, 'stocks-list'!C55:C5597=A55, ""))} -> AREB | C55: BIRK | D55: CROX | E55: DBI | F55: DECK | G55: FMFC | H55: FOSL | I55: FWDI | J55: NKE | K55: ONON | L55: RCKY | M55: SHOO | N55: VRA | O55: WEYS | P55: WWW
A56: Furnishings, Fixtures & Appliances | B56: {=TRANSPOSE(_xlfn._xlws.FILTER('stocks-list'!A56:A5598, 'stocks-list'!C56:C5598=A56, ""))} -> ALH | C56: AMWD | D56: ATER | E56: BOBS | F56: BSET | G56: COOK | H56: CRWS | I56: EFOI | J56: ETD | K56: FGI | L56: FLXS | M56: HBB | N56: HNI | O56: HOFT | P56: KEQU | Q56: LCUT | R56: LEG | S56: LOVE | T56: LZB | U56: MBC | V56: MHK | W56: MLKN | X56: MWYN | Y56: NCL | Z56: NTZ | AA56: PRPL | AB56: SGI | AC56: SN | AD56: SNBR | AE56: TILE | AF56: VIOT | AG56: VIRC | AH56: WHR | AI56: XWIN
A57: Gambling | B57: {=TRANSPOSE(_xlfn._xlws.FILTER('stocks-list'!A57:A5599, 'stocks-list'!C57:C5599=A57, ""))} -> BRAG | C57: BRSL | D57: CDRO | E57: CHDN | F57: DKNG | G57: FLUT | H57: GAMB | I57: INSE | J57: ROLR | K57: RSI | L57: SEGG | M57: SGHC
A58: Gold | B58: {=TRANSPOSE(_xlfn._xlws.FILTER('stocks-list'!A58:A5600, 'stocks-list'!C58:C5600=A58, ""))} -> AEM | C58: AGI | D58: ARIS | E58: AU | F58: AUGO | G58: AUST | H58: B | I58: BGL | J58: BTG | K58: CDE | L58: CGAU | M58: CMCL | N58: CNL | O58: CTGO | P58: DC | Q58: DRD | R58: EGO | S58: EQX | T58: FNV | U58: FSM | V58: GAU | W58: GFI | X58: GLDG | Y58: GROY | Z58: HMY | AA58: HYMC | AB58: IAG | AC58: IAUX | AD58: IDR | AE58: KGC | AF58: MINE | AG58: NAMM | AH58: NEM | AI58: NFGC | AJ58: NG | AK58: ODV | AL58: OR | AM58: ORLA | AN58: PAAS | AO58: PZG | AP58: RGLD | AQ58: SA | AR58: SSRM | AS58: THM | AT58: TRX | AU58: USAU | AV58: VGZ | AW58: WPM
A59: Grocery Stores | B59: {=TRANSPOSE(_xlfn._xlws.FILTER('stocks-list'!A59:A5601, 'stocks-list'!C59:C5601=A59, ""))} -> ACI | C59: DDL | D59: DNUT | E59: GO | F59: IMKTA | G59: KR | H59: MSS | I59: NGVC | J59: SFM | K59: VHUB | L59: VLGEA | M59: WMK
A60: Health Information Services | B60: {=TRANSPOSE(_xlfn._xlws.FILTER('stocks-list'!A60:A5602, 'stocks-list'!C60:C5602=A60, ""))} -> ACON | C60: AMWL | D60: BEAT | E60: BFRG | F60: BTSG | G60: CARL | H60: CCLD | I60: CERT | J60: CTEV | K60: DH | L60: DOCS | M60: DRIO | N60: EVH | O60: FORA | P60: GDRX | Q60: HCAT | R60: HCTI | S60: HNGE | T60: HQY | U60: HSTM | V60: HTFL | W60: LFMD | X60: MGRX | Y60: MNDR | Z60: NRC | AA60: OMCL | AB60: OMDA | AC60: ONMD | AD60: OPRX | AE60: PHR | AF60: PRVA | AG60: SDGR | AH60: SLP | AI60: SOPH | AJ60: SPOK | AK60: SY | AL60: TALK | AM60: TBRG | AN60: TDOC | AO60: TEM | AP60: TXG | AQ60: VEEV | AR60: VSEE | AS60: WAY | AT60: WEAV | AU60: WORX | AV60: ZCMD
A61: Healthcare Plans | B61: {=TRANSPOSE(_xlfn._xlws.FILTER('stocks-list'!A61:A5603, 'stocks-list'!C61:C5603=A61, ""))} -> ALHC | C61: CI | D61: CLOV | E61: CNC | F61: CVS | G61: ELV | H61: HUM | I61: MOH | J61: OSCR | K61: PGNY | L61: UNH
A62: Home Improvement Retail | B62: {=TRANSPOSE(_xlfn._xlws.FILTER('stocks-list'!A62:A5604, 'stocks-list'!C62:C5604=A62, ""))} -> FND | C62: HD | D62: HVT | E62: HVT.A | F62: LIVE | G62: LOW
A63: Household & Personal Products | B63: {=TRANSPOSE(_xlfn._xlws.FILTER('stocks-list'!A63:A5605, 'stocks-list'!C63:C5605=A63, ""))} -> ACU | C63: BYAH | D63: CHD | E63: CL | F63: CLX | G63: COTY | H63: DSY | I63: EL | J63: ELF | K63: EPC | L63: EWCZ | M63: GROV | N63: HELE | O63: HNST | P63: IPAR | Q63: KMB | R63: KVUE | S63: MAGN | T63: NUS | U63: NWL | V63: ODD | W63: PG | X63: PTNM | Y63: RAY | Z63: SKIN | AA63: SLSN | AB63: SPB | AC63: TANH | AD63: UG | AE63: UL | AF63: YSG
A64: Industrial Distribution | B64: {=TRANSPOSE(_xlfn._xlws.FILTER('stocks-list'!A64:A5606, 'stocks-list'!C64:C5606=A64, ""))} -> AIT | C64: BXC | D64: CNM | E64: DNOW | F64: DSGR | G64: DXPE | H64: EVI | I64: FAST | J64: FERG | K64: GIC | L64: GWW | M64: MSM | N64: POOL | O64: QXO | P64: REZI | Q64: SITE | R64: TITN | S64: TLIH | T64: WCC | U64: WSO | V64: WSO.B | W64: WXM | X64: XMTR
A65: Information Technology Services | B65: {=TRANSPOSE(_xlfn._xlws.FILTER('stocks-list'!A65:A5607, 'stocks-list'!C65:C5607=A65, ""))} -> ACN | C65: AIOS | D65: APLD | E65: ARBB | F65: ASGN | G65: AUR | H65: BBAI | I65: BR | J65: CACI | K65: CDW | L65: CIFR | M65: CLPS | N65: CLVT | O65: CNDT | P65: CNXC | Q65: CSPI | R65: CTM | S65: CTSH | T65: CYCU | U65: DAIC | V65: DTST | W65: DXC | X65: EPAM | Y65: EXLS | Z65: FIS | AA65: FORTY | AB65: G | AC65: GDS | AD65: GDYN | AE65: GIB | AF65: GLE | AG65: GLOB | AH65: GMM | AI65: HCKT | AJ65: IBEX | AK65: IBM | AL65: III | AM65: INFY | AN65: INGM | AO65: INOD | AP65: IT | AQ65: JDZG | AR65: JFU | AS65: JKHY | AT65: JZ | AU65: KD | AV65: LDOS | AW65: LZMH | AX65: MGRT | AY65: NABL | AZ65: NIQ | BA65: PENG | BB65: PONY | BC65: PSN | BD65: SAIC | BE65: SAIH | BF65: SHAZ | BG65: SLAI | BH65: TASK | BI65: TDTH | BJ65: TSSI | BK65: TTEC | BL65: TTGT | BM65: UIS | BN65: VEEA | BO65: VNET | BP65: VRRM | BQ65: VYX | BR65: WIT | BS65: WYY
A66: Infrastructure Operations | B66: {=TRANSPOSE(_xlfn._xlws.FILTER('stocks-list'!A66:A5608, 'stocks-list'!C66:C5608=A66, ""))} -> BEEP | C66: MWH
A67: Insurance - Diversified | B67: {=TRANSPOSE(_xlfn._xlws.FILTER('stocks-list'!A67:A5609, 'stocks-list'!C67:C5609=A67, ""))} -> AEG | C67: AIG | D67: BNT | E67: BRK.A | F67: BRK.B | G67: FIHL | H67: HIG | I67: IGIC | J67: SLF | K67: WDH | L67: XZO
A68: Insurance - Life | B68: {=TRANSPOSE(_xlfn._xlws.FILTER('stocks-list'!A68:A5610, 'stocks-list'!C68:C5610=A68, ""))} -> AFL | C68: BHF | D68: CIA | E68: CNO | F68: FG | G68: GL | H68: GNW | I68: JXN | J68: LIFE | K68: LNC | L68: MET | M68: MFC | N68: PRI | O68: PRU | P68: PUK | Q68: SNFCA | R68: UNM
A69: Insurance - Property & Casualty | B69: {=TRANSPOSE(_xlfn._xlws.FILTER('stocks-list'!A69:A5611, 'stocks-list'!C69:C5611=A69, ""))} -> AFG | C69: AII | D69: AIZ | E69: ALL | F69: ASIC | G69: BOW | H69: CB | I69: CINF | J69: CNA | K69: DGICA | L69: DGICB | M69: GBLI | N69: HCI | O69: HGTY | P69: HIPO | Q69: HMN | R69: HRTG | S69: KINS | T69: KMPR | U69: KNSL | V69: L | W69: LMND | X69: MCY | Y69: MKL | Z69: NODK | AA69: ORI | AB69: PGR | AC69: PLMR | AD69: PRA | AE69: PRCH | AF69: PRHI | AG69: RLI | AH69: ROOT | AI69: SAFT | AJ69: SIGI | AK69: SKWD | AL69: SLDE | AM69: STC | AN69: THG | AO69: TRUP | AP69: TRV | AQ69: UFCS | AR69: UVE | AS69: WRB | AT69: WTM
A70: Insurance - Reinsurance | B70: {=TRANSPOSE(_xlfn._xlws.FILTER('stocks-list'!A70:A5612, 'stocks-list'!C70:C5612=A70, ""))} -> EG | C70: GLRE | D70: HG | E70: KG | F70: OXBR | G70: RGA | H70: RNR | I70: SPNT
A71: Insurance - Specialty | B71: {=TRANSPOSE(_xlfn._xlws.FILTER('stocks-list'!A71:A5613, 'stocks-list'!C71:C5613=A71, ""))} -> ACT | C71: AGO | D71: AMSF | E71: AXS | F71: EIG | G71: ESNT | H71: FAF | I71: FNF | J71: ITIC | K71: JRVR | L71: MBI | M71: MTG | N71: NMIH | O71: OSG | P71: RDN | Q71: RYAN | R71: TIPT
A72: Insurance Brokers | B72: {=TRANSPOSE(_xlfn._xlws.FILTER('stocks-list'!A72:A5614, 'stocks-list'!C72:C5614=A72, ""))} -> AIFU | C72: AJG | D72: AON | E72: ARX | F72: BRO | G72: BWIN | H72: CRD.A | I72: CRD.B | J72: CRVL | K72: EHTH | L72: ERIE | M72: EZRA | N72: GOCO | O72: GSHD | P72: HUIZ | Q72: MRSH | R72: NP | S72: SLQT | T72: TWFG | U72: WTW | V72: XHG | W72: ZBAO
A73: Integrated Freight & Logistics | B73: {=TRANSPOSE(_xlfn._xlws.FILTER('stocks-list'!A73:A5615, 'stocks-list'!C73:C5615=A73, ""))} -> ATXG | C73: BTOC | D73: CHRW | E73: CIIT | F73: CJMB | G73: CRGO | H73: CTNT | I73: CYRX | J73: ELOG | K73: EXPD | L73: FDX | M73: FLX | N73: FWRD | O73: GVH | P73: GXO | Q73: HUBG | R73: HXHX | S73: JBHT | T73: JYD | U73: LSH | V73: LSTR | W73: NCEW | X73: PAL | Y73: PBI | Z73: PSIG | AA73: RLGT | AB73: SFWL | AC73: SGLY | AD73: SLGB | AE73: UPS | AF73: ZTO
A74: Internet Content & Information | B74: {=TRANSPOSE(_xlfn._xlws.FILTER('stocks-list'!A74:A5616, 'stocks-list'!C74:C5616=A74, ""))} -> ANGI | C74: AREN | D74: ATHM | E74: BIDU | F74: BILI | G74: BMBL | H74: BODI | I74: BZ | J74: BZFD | K74: CARS | L74: CCG | M74: CHAI | N74: CMCM | O74: DIBS | P74: DJT | Q74: DOYU | R74: EVER | S74: FENG | T74: FVRR | U74: GENI | V74: GETY | W74: GIBO | X74: GIFT | Y74: GITS | Z74: GOOG | AA74: GOOGL | AB74: GRPN | AC74: IAC | AD74: IZEA | AE74: JFIN | AF74: JOYY | AG74: LCFY | AH74: MAX | AI74: META | AJ74: MNY | AK74: MOMO | AL74: MTCH | AM74: NAMI | AN74: NBIS | AO74: NRDS | AP74: NXDR | AQ74: ONFO | AR74: OPRA | AS74: PERI | AT74: PINS | AU74: PODC | AV74: RDDT | AW74: RUM | AX74: SEAT | AY74: SJ | AZ74: SLE | BA74: SNAP | BB74: SOGP | BC74: SPOT | BD74: SSTK | BE74: STUB | BF74: TBLA | BG74: TEAD | BH74: TME | BI74: TRVG | BJ74: TZOO | BK74: UPWK | BL74: UPXI | BM74: VBIX | BN74: WB | BO74: WBTN | BP74: WSHP | BQ74: YELP | BR74: Z | BS74: ZDGE | BT74: ZG | BU74: ZH | BV74: ZIP
A75: Internet Retail | B75: {=TRANSPOSE(_xlfn._xlws.FILTER('stocks-list'!A75:A5617, 'stocks-list'!C75:C5617=A75, ""))} -> AMZN | C75: BABA | D75: BZUN | E75: CART | F75: CHWY | G75: CPNG | H75: DASH | I75: EBAY | J75: ETSY | K75: GLBE | L75: HEPS | M75: HOUR | N75: IPW | O75: JD | P75: JMIA | Q75: JWEL | R75: LGCB | S75: LITB | T75: LQDT | U75: MELI | V75: MI | W75: MOGU | X75: NEGG | Y75: NEXR | Z75: NHTC | AA75: OCG | AB75: PDD | AC75: QVCGA | AD75: RERE | AE75: RVLV | AF75: SE | AG75: TDUP | AH75: VIPS | AI75: W | AJ75: WBUY | AK75: WNW | AL75: YJ | AM75: ZKH
A76: Investment - Banking & Investment Services | B76: {=TRANSPOSE(_xlfn._xlws.FILTER('stocks-list'!A76:A5618, 'stocks-list'!C76:C5618=A76, ""))} -> OBTC
A77: Leisure | B77: {=TRANSPOSE(_xlfn._xlws.FILTER('stocks-list'!A77:A5619, 'stocks-list'!C77:C5619=A77, ""))} -> AGH | C77: AOUT | D77: AS | E77: CALY | F77: CLAR | G77: DOGZ | H77: ESCA | I77: FNKO | J77: FUN | K77: GDHG | L77: GOLF | M77: HAS | N77: HERE | O77: HWH | P77: JAKK | Q77: JOUT | R77: KMRK | S77: LTH | T77: LUCK | U77: MAT | V77: MMA | W77: MSGE | X77: NOMA | Y77: NWTG | Z77: OSW | AA77: PLBY | AB77: PLNT | AC77: PRKS | AD77: PTON | AE77: TRON | AF77: TRUG | AG77: XPOF | AH77: YETI
A78: Lodging | B78: {=TRANSPOSE(_xlfn._xlws.FILTER('stocks-list'!A78:A5620, 'stocks-list'!C78:C5620=A78, ""))} -> ATAT | C78: CHH | D78: CVEO | E78: GHG | F78: H | G78: HLT | H78: HTHT | I78: IHG | J78: INTG | K78: MAR | L78: WH
A79: Lumber & Wood Production | B79: {=TRANSPOSE(_xlfn._xlws.FILTER('stocks-list'!A79:A5621, 'stocks-list'!C79:C5621=A79, ""))} -> BCC | C79: JCTC | D79: NWGL | E79: SSD | F79: UFPI | G79: WFG
A80: Luxury Goods | B80: {=TRANSPOSE(_xlfn._xlws.FILTER('stocks-list'!A80:A5622, 'stocks-list'!C80:C5622=A80, ""))} -> BGI | C80: BRLT | D80: CPRI | E80: ELA | F80: LANV | G80: LUXE | H80: MOV | I80: REAL | J80: SIG | K80: SORA | L80: TPR
A81: Marine Shipping | B81: {=TRANSPOSE(_xlfn._xlws.FILTER('stocks-list'!A81:A5623, 'stocks-list'!C81:C5623=A81, ""))} -> ASC | C81: BWLP | D81: CCEC | E81: CISS | F81: CMDB | G81: CMRE | H81: CTRM | I81: DAC | J81: DSX | K81: ECO | L81: EDRY | M81: EHLD | N81: ESEA | O81: GASS | P81: GLBS | Q81: GNK | R81: GSL | S81: HAFN | T81: HMR | U81: HSHP | V81: HTCO | W81: ICON | X81: KEX | Y81: MATX | Z81: NCT | AA81: NMM | AB81: PANL | AC81: PSHG | AD81: RUBI | AE81: SB | AF81: SBLK | AG81: SFL | AH81: SHIP | AI81: SMHI | AJ81: SVRN | AK81: UFG | AL81: USEA | AM81: VNTG | AN81: ZIM
A82: Medical - Specialties | B82: {=TRANSPOSE(_xlfn._xlws.FILTER('stocks-list'!A82:A5624, 'stocks-list'!C82:C5624=A82, ""))} -> SI
A83: Medical Care Facilities | B83: {=TRANSPOSE(_xlfn._xlws.FILTER('stocks-list'!A83:A5625, 'stocks-list'!C83:C5625=A83, ""))} -> ADUS | C83: AGL | D83: AIRS | E83: AMN | F83: AMS | G83: ARDT | H83: ASTH | I83: AUNA | J83: AVAH | K83: BKD | L83: BMGL | M83: BTMD | N83: CCEL | O83: CCM | P83: CCRN | Q83: CHE | R83: CMPS | S83: CON | T83: CYH | U83: DCGO | V83: DVA | W83: EHAB | X83: EHC | Y83: ENSG | Z83: FMS | AA83: GRDN | AB83: HCA | AC83: HCSG | AD83: INNV | AE83: JYNT | AF83: LFST | AG83: MCTA | AH83: MD | AI83: NHC | AJ83: NIVF | AK83: NUTX | AL83: OPCH | AM83: PACS | AN83: PARK | AO83: PIII | AP83: PNTG | AQ83: SEM | AR83: SGRY | AS83: SNDA | AT83: SRTA | AU83: THC | AV83: TOI | AW83: UHS | AX83: USPH | AY83: WW
A84: Medical Devices | B84: {=TRANSPOSE(_xlfn._xlws.FILTER('stocks-list'!A84:A5626, 'stocks-list'!C84:C5626=A84, ""))} -> ADGM | C84: AEMD | D84: AHCO | E84: AMIX | F84: AORT | G84: APYX | H84: ARAY | I84: ATEC | J84: AVNS | K84: AXGN | L84: BBNX | M84: BDMD | N84: BFLY | O84: BIO | P84: BIO.B | Q84: BJDX | R84: BMRA | S84: BRKR | T84: BSX | U84: BVS | V84: BWAY | W84: CATX | X84: CBLL | Y84: CERS | Z84: CLPT | AA84: CNMD | AB84: COCH | AC84: CODX | AD84: CTKB | AE84: CTSO | AF84: CV | AG84: CVRX | AH84: DCTH | AI84: DXCM | AJ84: ECOR | AK84: ELMD | AL84: ELUT | AM84: ENOV | AN84: ESTA | AO84: EW | AP84: FEED | AQ84: GEHC | AR84: GKOS | AS84: GMED | AT84: HAE | AU84: HSCS | AV84: HYPR | AW84: IART | AX84: ICCM | AY84: IINN | AZ84: INBS | BA84: INFU | BB84: INGN | BC84: INMD | BD84: INSP | BE84: IRIX | BF84: IRMD | BG84: IRTC | BH84: ITGR | BI84: ITOC | BJ84: IVF | BK84: KIDS | BL84: LAB | BM84: LFWD | BN84: LIVN | BO84: LMRI | BP84: LNSR | BQ84: LUCD | BR84: LUNG | BS84: MASI | BT84: MASS | BU84: MDAI | BV84: MDT | BW84: MODD | BX84: MXCT | BY84: MYO | BZ84: NEOG | CA84: NMTC | CB84: NNOX | CC84: NPCE | CD84: NSPR | CE84: NSYS | CF84: NUWE | CG84: NVCR | CH84: NVNO | CI84: NXL | CJ84: OFIX | CK84: OM | CL84: OWLT | CM84: PACB | CN84: PAVM | CO84: PEN | CP84: PFSA | CQ84: PHG | CR84: PLSM | CS84: PMI | CT84: POAS | CU84: PODD | CV84: PRCT | CW84: PROF | CX84: QDEL | CY84: QSI | CZ84: QTI | DA84: QTRX | DB84: RCEL | DC84: RPID | DD84: RXST | DE84: SENS | DF84: SERA | DG84: SGHT | DH84: SIBN | DI84: SINT | DJ84: SNN | DK84: SNWV | DL84: SRTS | DM84: SSII | DN84: STE | DO84: STIM | DP84: SYK | DQ84: TCMD | DR84: TELA | DS84: TIVC | DT84: TLSI | DU84: TMCI | DV84: TMDX | DW84: TNDM | DX84: TNON | DY84: TRIB | DZ84: UFPT | EA84: VMD | EB84: VNRX | EC84: VREX | ED84: VTAK | EE84: VVOS | EF84: WOK | EG84: XAIR | EH84: XTNT | EI84: ZBH
A85: Medical Distribution | B85: {=TRANSPOSE(_xlfn._xlws.FILTER('stocks-list'!A85:A5627, 'stocks-list'!C85:C5627=A85, ""))} -> AHG | C85: CAH | D85: COR | E85: COSM | F85: EDAP | G85: EMPG | H85: HSIC | I85: MCK | J85: SNYR | K85: YI
A86: Medical Instruments & Supplies | B86: {=TRANSPOSE(_xlfn._xlws.FILTER('stocks-list'!A86:A5628, 'stocks-list'!C86:C5628=A86, ""))} -> ALC | C86: ALGN | D86: ANGO | E86: ATR | F86: ATRC | G86: AVR | H86: AVTR | I86: AZTA | J86: BAX | K86: BDX | L86: BLCO | M86: BLFS | N86: BNGO | O86: COO | P86: CUPR | Q86: DXR | R86: EKSO | S86: EMBC | T86: FEMY | U86: GCTK | V86: HBIO | W86: HOLX | X86: ICUI | Y86: ISRG | Z86: KMTS | AA86: KRMD | AB86: LMAT | AC86: LUCY | AD86: MBOT | AE86: MDLN | AF86: MLSS | AG86: MMED | AH86: MMSI | AI86: NEPH | AJ86: NNNN | AK86: NVST | AL86: NXGL | AM86: NYXH | AN86: OSUR | AO86: PDEX | AP86: PLSE | AQ86: POCI | AR86: RGEN | AS86: RGNT | AT86: RMD | AU86: RVP | AV86: SMTI | AW86: SOLV | AX86: STAA | AY86: STSS | AZ86: STVN | BA86: STXS | BB86: TFX | BC86: UTMD | BD86: WRBY | BE86: WST | BF86: XRAY | BG86: ZJYL | BH86: ZTEK
A87: Metal Fabrication | B87: {=TRANSPOSE(_xlfn._xlws.FILTER('stocks-list'!A87:A5629, 'stocks-list'!C87:C5629=A87, ""))} -> AP | C87: ATI | D87: CMC | E87: CRS | F87: ESAB | G87: GPGI | H87: HIHO | I87: IIIN | J87: MEC | K87: MLI | L87: MTEN | M87: OLOX | N87: PRLB | O87: RYZ | P87: TG | Q87: TPCS | R87: TRSG | S87: WOR
A88: Mortgage Finance | B88: {=TRANSPOSE(_xlfn._xlws.FILTER('stocks-list'!A88:A5630, 'stocks-list'!C88:C5630=A88, ""))} -> BETR | C88: BLNE | D88: CNF | E88: GHI | F88: IOR | G88: LDI | H88: ONIT | I88: PAPL | J88: PFSI | K88: RKT | L88: UWMC | M88: VEL | N88: WD
A89: Oil & Gas | B89: {=TRANSPOSE(_xlfn._xlws.FILTER('stocks-list'!A89:A5631, 'stocks-list'!C89:C5631=A89, ""))} -> ALPS
A90: Oil & Gas Drilling | B90: {=TRANSPOSE(_xlfn._xlws.FILTER('stocks-list'!A90:A5632, 'stocks-list'!C90:C5632=A90, ""))} -> BORR | C90: HP | D90: NBR | E90: NE | F90: PDS | G90: PTEN | H90: RIG | I90: SDRL | J90: SOC
A91: Oil & Gas Equipment & Services | B91: {=TRANSPOSE(_xlfn._xlws.FILTER('stocks-list'!A91:A5633, 'stocks-list'!C91:C5633=A91, ""))} -> AESI | C91: AROC | D91: BKR | E91: CLB | F91: DTI | G91: DWSN | H91: EFXT | I91: FET | J91: FLOC | K91: FTI | L91: FTK | M91: GEOS | N91: HAL | O91: HLX | P91: HMH | Q91: INVX | R91: KGS | S91: KLXE | T91: LB | U91: LBRT | V91: LSE | W91: NCSM | X91: NESR | Y91: NEXT | Z91: NGS | AA91: NINE | AB91: NOA | AC91: NOV | AD91: NPKI | AE91: OII | AF91: OIS | AG91: OMSE | AH91: PUMP | AI91: RCON | AJ91: RES | AK91: RNGR | AL91: SEI | AM91: SLB | AN91: SND | AO91: STAK | AP91: TDW | AQ91: TS | AR91: USAC | AS91: VAL | AT91: VTOL | AU91: WBI | AV91: WFRD | AW91: WHD | AX91: WTTR | AY91: XPRO
A92: Oil & Gas Exploration & Production | B92: {=TRANSPOSE(_xlfn._xlws.FILTER('stocks-list'!A92:A5634, 'stocks-list'!C92:C5634=A92, ""))} -> AMPY | C92: ANNA | D92: APA | E92: AR | F92: BATL | G92: BKV | H92: BRN | I92: BSM | J92: BTE | K92: CHRD | L92: CKX | M92: CNQ | N92: CNX | O92: COP | P92: CRC | Q92: CRGY | R92: CRK | S92: CRT | T92: CTRA | U92: DMLP | V92: DVN | W92: EGY | X92: EOG | Y92: EONR | Z92: EP | AA92: EPM | AB92: EPSN | AC92: EQT | AD92: EXE | AE92: FANG | AF92: FTW | AG92: GFR | AH92: GPOR | AI92: GPRK | AJ92: GRNT | AK92: GTE | AL92: HPK | AM92: INDO | AN92: INR | AO92: KGEI | AP92: KOS | AQ92: KRP | AR92: MGY | AS92: MNR | AT92: MTDR | AU92: MTR | AV92: MUR | AW92: MXC | AX92: NOG | AY92: NRT | AZ92: OBE | BA92: OVV | BB92: OXY | BC92: PED | BD92: PNRG | BE92: PR | BF92: PROP | BG92: PRT | BH92: PVL | BI92: REI | BJ92: REPX | BK92: RRC | BL92: SD | BM92: SJT | BN92: SM | BO92: TALO | BP92: TBN | BQ92: TPET | BR92: TPL | BS92: TXO | BT92: USEG | BU92: VET | BV92: VIST | BW92: VOC | BX92: VTS | BY92: WDS | BZ92: WTI
A93: Oil & Gas Integrated | B93: {=TRANSPOSE(_xlfn._xlws.FILTER('stocks-list'!A93:A5635, 'stocks-list'!C93:C5635=A93, ""))} -> BP | C93: CVE | D93: CVX | E93: DEC | F93: E | G93: EC | H93: EQNR | I93: IMO | J93: NFG | K93: PBR | L93: PBR.A | M93: SHEL | N93: SKYQ | O93: SLNG | P93: SU | Q93: TGS | R93: TTE | S93: XOM | T93: YPF
A94: Oil & Gas Midstream | B94: {=TRANSPOSE(_xlfn._xlws.FILTER('stocks-list'!A94:A5636, 'stocks-list'!C94:C5636=A94, ""))} -> AM | C94: BANL | D94: CMBT | E94: CQP | F94: DHT | G94: DLNG | H94: DTM | I94: EE | J94: ENB | K94: EPD | L94: ET | M94: FLNG | N94: FRO | O94: GEL | P94: GLNG | Q94: GLP | R94: HESM | S94: IMPP | T94: INSW | U94: KMI | V94: KNOP | W94: KNTK | X94: LNG | Y94: LPG | Z94: MARPS | AA94: MMLP | AB94: MPLX | AC94: NAT | AD94: NFE | AE94: NGL | AF94: NVGS | AG94: OKE | AH94: PAA | AI94: PAGP | AJ94: PBA | AK94: PBT | AL94: PXS | AM94: RBNE | AN94: SBR | AO94: SMC | AP94: SOBO | AQ94: STNG | AR94: SUNC | AS94: TEN | AT94: TK | AU94: TMDE | AV94: TNK | AW94: TOPS | AX94: TORO | AY94: TRGP | AZ94: TRMD | BA94: TRP | BB94: VG | BC94: VNOM | BD94: WES | BE94: WMB
A95: Oil & Gas Refining & Marketing | B95: {=TRANSPOSE(_xlfn._xlws.FILTER('stocks-list'!A95:A5637, 'stocks-list'!C95:C5637=A95, ""))} -> APC | C95: CAPL | D95: CLNE | E95: CSAN | F95: CVI | G95: DINO | H95: DK | I95: DKL | J95: DLXY | K95: IEP | L95: MPC | M95: PARR | N95: PBF | O95: PSX | P95: SGU | Q95: SUN | R95: UGP | S95: VLO | T95: WKC
A96: Other | B96: {=TRANSPOSE(_xlfn._xlws.FILTER('stocks-list'!A96:A5638, 'stocks-list'!C96:C5638=A96, ""))} -> CAST | C96: MAKO | D96: SSM | E96: VMET
A97: Other Industrial Metals & Mining | B97: {=TRANSPOSE(_xlfn._xlws.FILTER('stocks-list'!A97:A5639, 'stocks-list'!C97:C5639=A97, ""))} -> ALM | C97: ALOY | D97: ATLX | E97: BHP | F97: BMM | G97: CHNR | H97: CMP | I97: CRML | J97: ELBM | K97: ELVR | L97: EMAT | M97: FMST | N97: FNUC | O97: FURY | P97: GRO | Q97: GSM | R97: IONR | S97: IPX | T97: LAC | U97: LAR | V97: LGO | W97: LZM | X97: MP | Y97: MTRN | Z97: NAK | AA97: NB | AB97: NEXA | AC97: NEXM | AD97: NMG | AE97: NVA | AF97: OMEX | AG97: RIO | AH97: SCZM | AI97: SGML | AJ97: SKE | AK97: SLI | AL97: TECK | AM97: TII | AN97: TMC | AO97: TMQ | AP97: UAMY | AQ97: USAR | AR97: USAS | AS97: USGO | AT97: VALE | AU97: VZLA | AV97: WRN | AW97: WWR | AX97: XPL
A98: Other Precious Metals & Mining | B98: {=TRANSPOSE(_xlfn._xlws.FILTER('stocks-list'!A98:A5640, 'stocks-list'!C98:C5640=A98, ""))} -> ASM | C98: BVN | D98: ELE | E98: GMTL | F98: GORO | G98: GRML | H98: HL | I98: ITRG | J98: LODE | K98: MTA | L98: MUX | M98: OGC | N98: PLG | O98: PPTA | P98: SBSW | Q98: SLSR | R98: TFPM | S98: VOXR
A99: Packaged Foods | B99: {=TRANSPOSE(_xlfn._xlws.FILTER('stocks-list'!A99:A5641, 'stocks-list'!C99:C5641=A99, ""))} -> ATPC | C99: BGS | D99: BHST | E99: BOF | F99: BRBR | G99: BRCC | H99: BRID | I99: BRLS | J99: BYND | K99: CAG | L99: CENT | M99: CENTA | N99: CLNN | O99: COOT | P99: CPB | Q99: DAR | R99: DDC | S99: FAMI | T99: FARM | U99: FLO | V99: FRPT | W99: FTLF | X99: GIS | Y99: HAIN | Z99: HLF | AA99: HRL | AB99: INGR | AC99: JBS | AD99: JBSS | AE99: JJSF | AF99: JVA | AG99: KHC | AH99: LFVN | AI99: LSF | AJ99: LW | AK99: LWAY | AL99: MAMA | AM99: MEHA | AN99: MICC | AO99: MKC | AP99: MKC.V | AQ99: MZTI | AR99: NAII | AS99: NATR | AT99: NCRA | AU99: NOMD | AV99: OFRM | AW99: ORIS | AX99: OTLY | AY99: PAVS | AZ99: POST | BA99: PPC | BB99: RKDA | BC99: SENEA | BD99: SENEB | BE99: SFD | BF99: SJM | BG99: SMPL | BH99: SRXH | BI99: STKH | BJ99: USNA | BK99: UTZ | BL99: WEST | BM99: WYHG
A100: Packaging & Containers | B100: {=TRANSPOSE(_xlfn._xlws.FILTER('stocks-list'!A100:A5642, 'stocks-list'!C100:C5642=A100, ""))} -> AMBP | C100: AMCR | D100: AVY | E100: BALL | F100: CCK | G100: DSS | H100: GEF | I100: GEF.B | J100: GPK | K100: IP | L100: KRT | M100: MGIH | N100: MYE | O100: OI | P100: ORBS | Q100: PACK | R100: PKG | S100: REYN | T100: SEE | U100: SLGN | V100: SON | W100: SW | X100: TRS | Y100: YHGJ
...

Sheet Sheet1
A1: {='stocks-list'!A2:B5544} -> A | B1: Agilent Technologies, Inc. | C1: =A1&" - "&B1 -> A - Agilent Technologies, Inc.
A2: AA | B2: Alcoa Corporation | C2: =A2&" - "&B2 -> AA - Alcoa Corporation
A3: AACB | B3: Artius II Acquisition Inc. | C3: =A3&" - "&B3 -> AACB - Artius II Acquisition Inc.
A4: AACG | B4: ATA Creativity Global | C4: =A4&" - "&B4 -> AACG - ATA Creativity Global
A5: AACI | B5: Armada Acquisition Corp. III | C5: =A5&" - "&B5 -> AACI - Armada Acquisition Corp. III
A6: AACO | B6: Abony Acquisition Corp. I | C6: =A6&" - "&B6 -> AACO - Abony Acquisition Corp. I
A7: AACP | B7: Apogee Acquisition Corp | C7: =A7&" - "&B7 -> AACP - Apogee Acquisition Corp
A8: AAL | B8: American Airlines Group Inc. | C8: =A8&" - "&B8 -> AAL - American Airlines Group Inc.
A9: AAME | B9: Atlantic American Corporation | C9: =A9&" - "&B9 -> AAME - Atlantic American Corporation
A10: AAMI | B10: Acadian Asset Management Inc. | C10: =A10&" - "&B10 -> AAMI - Acadian Asset Management Inc.
A11: AAOI | B11: Applied Optoelectronics, Inc. | C11: =A11&" - "&B11 -> AAOI - Applied Optoelectronics, Inc.
A12: AAON | B12: AAON, Inc. | C12: =A12&" - "&B12 -> AAON - AAON, Inc.
A13: AAP | B13: Advance Auto Parts, Inc. | C13: =A13&" - "&B13 -> AAP - Advance Auto Parts, Inc.
... A5543: ZYME | B5543: Zymeworks Inc. | C5543: =A5543&" - "&B5543 -> ZYME - Zymeworks Inc.
